[
  {
    "exchange": "dydx",
    "market_type": "CROSS",
    "symbol_raw": "BTC-USD",
    "leverage_max": 50,
    "price_usd": 62615.2889,
    "volume_24h_usd": 35991795.614,
    "open_interest_base": 327.3699,
    "open_interest_usd": 20498360.86566411,
    "daily_snapshot": "2026-07-05"
  },
  {
    "exchange": "dydx",
    "market_type": "CROSS",
    "symbol_raw": "ETH-USD",
    "leverage_max": 50,
    "price_usd": 1760.313811,
    "volume_24h_usd": 24366387.9015,
    "open_interest_base": 12195.324,
    "open_interest_usd": 21467597.266819764,
    "daily_snapshot": "2026-07-05"
  },
  {
    "exchange": "dydx",
    "market_type": "CROSS",
    "symbol_raw": "LINK-USD",
    "leverage_max": 10,
    "price_usd": 7.884674194,
    "volume_24h_usd": 5919.814,
    "open_interest_base": 34059.0,
    "open_interest_usd": 268544.118373446,
    "daily_snapshot": "2026-07-05"
  },
  {
    "exchange": "dydx",
    "market_type": "CROSS",
    "symbol_raw": "MATIC-USD",
    "leverage_max": 10,
    "price_usd": 0.3932407381,
    "volume_24h_usd": 0.0,
    "open_interest_base": 0.0,
    "open_interest_usd": 0.0,
    "daily_snapshot": "2026-07-05"
  },
  {
    "exchange": "dydx",
    "market_type": "CROSS",
    "symbol_raw": "CRV-USD",
    "leverage_max": 10,
    "price_usd": 0.2088,
    "volume_24h_usd": 113.95,
    "open_interest_base": 171000.0,
    "open_interest_usd": 35704.8,
    "daily_snapshot": "2026-07-05"
  },
  {
    "exchange": "dydx",
    "market_type": "CROSS",
    "symbol_raw": "SOL-USD",
    "leverage_max": 20,
    "price_usd": 80.54373843,
    "volume_24h_usd": 13182604.202,
    "open_interest_base": 65812.9,
    "open_interest_usd": 5300817.002919747,
    "daily_snapshot": "2026-07-05"
  },
  {
    "exchange": "dydx",
    "market_type": "CROSS",
    "symbol_raw": "ADA-USD",
    "leverage_max": 10,
    "price_usd": 0.1856,
    "volume_24h_usd": 25910.704,
    "open_interest_base": 1423220.0,
    "open_interest_usd": 264149.632,
    "daily_snapshot": "2026-07-05"
  },
  {
    "exchange": "dydx",
    "market_type": "CROSS",
    "symbol_raw": "AVAX-USD",
    "leverage_max": 10,
    "price_usd": 6.87,
    "volume_24h_usd": 34900.9103,
    "open_interest_base": 14652.2,
    "open_interest_usd": 100660.614,
    "daily_snapshot": "2026-07-05"
  },
  {
    "exchange": "dydx",
    "market_type": "CROSS",
    "symbol_raw": "FIL-USD",
    "leverage_max": 10,
    "price_usd": 0.779,
    "volume_24h_usd": 1535.1882,
    "open_interest_base": 63395.0,
    "open_interest_usd": 49384.705,
    "daily_snapshot": "2026-07-05"
  },
  {
    "exchange": "dydx",
    "market_type": "CROSS",
    "symbol_raw": "LTC-USD",
    "leverage_max": 10,
    "price_usd": 44.80654789,
    "volume_24h_usd": 11248.941,
    "open_interest_base": 11642.2,
    "open_interest_usd": 521646.791844958,
    "daily_snapshot": "2026-07-05"
  },
  {
    "exchange": "dydx",
    "market_type": "CROSS",
    "symbol_raw": "DOGE-USD",
    "leverage_max": 10,
    "price_usd": 0.07583842989,
    "volume_24h_usd": 79434.751,
    "open_interest_base": 2686300.0,
    "open_interest_usd": 203724.77421350701,
    "daily_snapshot": "2026-07-05"
  },
  {
    "exchange": "dydx",
    "market_type": "CROSS",
    "symbol_raw": "ATOM-USD",
    "leverage_max": 10,
    "price_usd": 1.55000787,
    "volume_24h_usd": 7926.667,
    "open_interest_base": 40464.0,
    "open_interest_usd": 62719.51845168,
    "daily_snapshot": "2026-07-05"
  },
  {
    "exchange": "dydx",
    "market_type": "CROSS",
    "symbol_raw": "DOT-USD",
    "leverage_max": 10,
    "price_usd": 0.868350838,
    "volume_24h_usd": 3785.415,
    "open_interest_base": 119620.0,
    "open_interest_usd": 103872.12724156,
    "daily_snapshot": "2026-07-05"
  },
  {
    "exchange": "dydx",
    "market_type": "CROSS",
    "symbol_raw": "UNI-USD",
    "leverage_max": 10,
    "price_usd": 3.103089711,
    "volume_24h_usd": 22841.1407,
    "open_interest_base": 38861.0,
    "open_interest_usd": 120589.169259171,
    "daily_snapshot": "2026-07-05"
  },
  {
    "exchange": "dydx",
    "market_type": "CROSS",
    "symbol_raw": "BCH-USD",
    "leverage_max": 10,
    "price_usd": 236.7579452,
    "volume_24h_usd": 37374.4,
    "open_interest_base": 219.31,
    "open_interest_usd": 51923.384961812,
    "daily_snapshot": "2026-07-05"
  },
  {
    "exchange": "dydx",
    "market_type": "CROSS",
    "symbol_raw": "TRX-USD",
    "leverage_max": 10,
    "price_usd": 0.32667344223,
    "volume_24h_usd": 18316.723,
    "open_interest_base": 521000.0,
    "open_interest_usd": 170196.86340183,
    "daily_snapshot": "2026-07-05"
  },
  {
    "exchange": "dydx",
    "market_type": "CROSS",
    "symbol_raw": "NEAR-USD",
    "leverage_max": 10,
    "price_usd": 1.944867766,
    "volume_24h_usd": 2337.734,
    "open_interest_base": 37408.0,
    "open_interest_usd": 72753.613390528,
    "daily_snapshot": "2026-07-05"
  },
  {
    "exchange": "dydx",
    "market_type": "CROSS",
    "symbol_raw": "MKR-USD",
    "leverage_max": 5,
    "price_usd": 1763.39,
    "volume_24h_usd": 0.0,
    "open_interest_base": 0.0,
    "open_interest_usd": 0.0,
    "daily_snapshot": "2026-07-05"
  },
  {
    "exchange": "dydx",
    "market_type": "CROSS",
    "symbol_raw": "XLM-USD",
    "leverage_max": 10,
    "price_usd": 0.1986710497,
    "volume_24h_usd": 3742.036,
    "open_interest_base": 299040.0,
    "open_interest_usd": 59410.590702288,
    "daily_snapshot": "2026-07-05"
  },
  {
    "exchange": "dydx",
    "market_type": "CROSS",
    "symbol_raw": "ETC-USD",
    "leverage_max": 10,
    "price_usd": 7.10024559,
    "volume_24h_usd": 6103.6905,
    "open_interest_base": 3254.2,
    "open_interest_usd": 23105.619198977998,
    "daily_snapshot": "2026-07-05"
  },
  {
    "exchange": "dydx",
    "market_type": "CROSS",
    "symbol_raw": "COMP-USD",
    "leverage_max": 5,
    "price_usd": 16.74452343,
    "volume_24h_usd": 31.272,
    "open_interest_base": 3814.9,
    "open_interest_usd": 63878.682433107,
    "daily_snapshot": "2026-07-05"
  },
  {
    "exchange": "dydx",
    "market_type": "CROSS",
    "symbol_raw": "WLD-USD",
    "leverage_max": 10,
    "price_usd": 0.408155106,
    "volume_24h_usd": 7559.284,
    "open_interest_base": 133665.0,
    "open_interest_usd": 54556.05224349,
    "daily_snapshot": "2026-07-05"
  },
  {
    "exchange": "dydx",
    "market_type": "CROSS",
    "symbol_raw": "APE-USD",
    "leverage_max": 5,
    "price_usd": 0.142480237,
    "volume_24h_usd": 0.0,
    "open_interest_base": 136001.0,
    "open_interest_usd": 19377.454712237002,
    "daily_snapshot": "2026-07-05"
  },
  {
    "exchange": "dydx",
    "market_type": "CROSS",
    "symbol_raw": "APT-USD",
    "leverage_max": 10,
    "price_usd": 0.615269311,
    "volume_24h_usd": 911.6177,
    "open_interest_base": 77541.0,
    "open_interest_usd": 47708.597644251,
    "daily_snapshot": "2026-07-05"
  },
  {
    "exchange": "dydx",
    "market_type": "CROSS",
    "symbol_raw": "ARB-USD",
    "leverage_max": 10,
    "price_usd": 0.078552868,
    "volume_24h_usd": 7021.51384,
    "open_interest_base": 453651.0,
    "open_interest_usd": 35635.587121068,
    "daily_snapshot": "2026-07-05"
  },
  {
    "exchange": "dydx",
    "market_type": "CROSS",
    "symbol_raw": "BLUR-USD",
    "leverage_max": 5,
    "price_usd": 0.0148795842,
    "volume_24h_usd": 0.0,
    "open_interest_base": 747620.0,
    "open_interest_usd": 11124.274739604,
    "daily_snapshot": "2026-07-05"
  },
  {
    "exchange": "dydx",
    "market_type": "CROSS",
    "symbol_raw": "LDO-USD",
    "leverage_max": 5,
    "price_usd": 0.265840495,
    "volume_24h_usd": 29.9566,
    "open_interest_base": 117327.0,
    "open_interest_usd": 31190.267756865,
    "daily_snapshot": "2026-07-05"
  },
  {
    "exchange": "dydx",
    "market_type": "CROSS",
    "symbol_raw": "OP-USD",
    "leverage_max": 10,
    "price_usd": 0.105727048,
    "volume_24h_usd": 247.3014,
    "open_interest_base": 454911.0,
    "open_interest_usd": 48096.397132728,
    "daily_snapshot": "2026-07-05"
  },
  {
    "exchange": "dydx",
    "market_type": "CROSS",
    "symbol_raw": "PEPE-USD",
    "leverage_max": 10,
    "price_usd": 2.6554067559e-06,
    "volume_24h_usd": 10399.395,
    "open_interest_base": 8840000000.0,
    "open_interest_usd": 23473.795722156,
    "daily_snapshot": "2026-07-05"
  },
  {
    "exchange": "dydx",
    "market_type": "CROSS",
    "symbol_raw": "SEI-USD",
    "leverage_max": 5,
    "price_usd": 0.0484183328,
    "volume_24h_usd": 898.8941,
    "open_interest_base": 1955950.0,
    "open_interest_usd": 94703.83804016,
    "daily_snapshot": "2026-07-05"
  },
  {
    "exchange": "dydx",
    "market_type": "CROSS",
    "symbol_raw": "SHIB-USD",
    "leverage_max": 10,
    "price_usd": 4.313566776e-06,
    "volume_24h_usd": 1796.86,
    "open_interest_base": 5875000000.0,
    "open_interest_usd": 25342.204809000003,
    "daily_snapshot": "2026-07-05"
  },
  {
    "exchange": "dydx",
    "market_type": "CROSS",
    "symbol_raw": "SUI-USD",
    "leverage_max": 10,
    "price_usd": 0.7416205908,
    "volume_24h_usd": 7380.07,
    "open_interest_base": 130160.0,
    "open_interest_usd": 96529.336098528,
    "daily_snapshot": "2026-07-05"
  },
  {
    "exchange": "dydx",
    "market_type": "CROSS",
    "symbol_raw": "XRP-USD",
    "leverage_max": 10,
    "price_usd": 1.1299744333,
    "volume_24h_usd": 149669.787,
    "open_interest_base": 821830.0,
    "open_interest_usd": 928646.8885189389,
    "daily_snapshot": "2026-07-05"
  },
  {
    "exchange": "dydx",
    "market_type": "CROSS",
    "symbol_raw": "TIA-USD",
    "leverage_max": 10,
    "price_usd": 0.38694684,
    "volume_24h_usd": 2306.38065,
    "open_interest_base": 197863.9,
    "open_interest_usd": 76562.810855076,
    "daily_snapshot": "2026-07-05"
  },
  {
    "exchange": "dydx",
    "market_type": "CROSS",
    "symbol_raw": "EIGEN-USD",
    "leverage_max": 5,
    "price_usd": 0.225022359,
    "volume_24h_usd": 0.0,
    "open_interest_base": 9102.0,
    "open_interest_usd": 2048.1535116180003,
    "daily_snapshot": "2026-07-05"
  },
  {
    "exchange": "dydx",
    "market_type": "CROSS",
    "symbol_raw": "JUP-USD",
    "leverage_max": 5,
    "price_usd": 0.2375384739,
    "volume_24h_usd": 438.271,
    "open_interest_base": 161700.0,
    "open_interest_usd": 38409.97122963,
    "daily_snapshot": "2026-07-05"
  },
  {
    "exchange": "dydx",
    "market_type": "CROSS",
    "symbol_raw": "AAVE-USD",
    "leverage_max": 10,
    "price_usd": 88.03351445,
    "volume_24h_usd": 4811.555,
    "open_interest_base": 1198.0,
    "open_interest_usd": 105464.15031109999,
    "daily_snapshot": "2026-07-05"
  },
  {
    "exchange": "dydx",
    "market_type": "CROSS",
    "symbol_raw": "BNB-USD",
    "leverage_max": 10,
    "price_usd": 578.3649676,
    "volume_24h_usd": 42586.0754,
    "open_interest_base": 292.55,
    "open_interest_usd": 169200.67127138,
    "daily_snapshot": "2026-07-05"
  },
  {
    "exchange": "dydx",
    "market_type": "CROSS",
    "symbol_raw": "JTO-USD",
    "leverage_max": 5,
    "price_usd": 0.717547945,
    "volume_24h_usd": 89.1214,
    "open_interest_base": 4569.0,
    "open_interest_usd": 3278.476560705,
    "daily_snapshot": "2026-07-05"
  },
  {
    "exchange": "dydx",
    "market_type": "CROSS",
    "symbol_raw": "ORDI-USD",
    "leverage_max": 5,
    "price_usd": 3.26476363,
    "volume_24h_usd": 3602.7168,
    "open_interest_base": 4834.3,
    "open_interest_usd": 15782.846816509,
    "daily_snapshot": "2026-07-05"
  },
  {
    "exchange": "dydx",
    "market_type": "CROSS",
    "symbol_raw": "EOS-USD",
    "leverage_max": 10,
    "price_usd": 0.8167633526,
    "volume_24h_usd": 0.0,
    "open_interest_base": 0.0,
    "open_interest_usd": 0.0,
    "daily_snapshot": "2026-07-05"
  },
  {
    "exchange": "dydx",
    "market_type": "CROSS",
    "symbol_raw": "ICP-USD",
    "leverage_max": 5,
    "price_usd": 2.177,
    "volume_24h_usd": 1284.57078,
    "open_interest_base": 23339.8,
    "open_interest_usd": 50810.7446,
    "daily_snapshot": "2026-07-05"
  },
  {
    "exchange": "dydx",
    "market_type": "CROSS",
    "symbol_raw": "DYM-USD",
    "leverage_max": 5,
    "price_usd": 0.016338889,
    "volume_24h_usd": 114.524,
    "open_interest_base": 375914.0,
    "open_interest_usd": 6142.017119546,
    "daily_snapshot": "2026-07-05"
  },
  {
    "exchange": "dydx",
    "market_type": "CROSS",
    "symbol_raw": "STRK-USD",
    "leverage_max": 5,
    "price_usd": 0.030650173,
    "volume_24h_usd": 15.37461,
    "open_interest_base": 1395047.0,
    "open_interest_usd": 42758.431893131,
    "daily_snapshot": "2026-07-05"
  },
  {
    "exchange": "dydx",
    "market_type": "CROSS",
    "symbol_raw": "FET-USD",
    "leverage_max": 5,
    "price_usd": 1.34838175,
    "volume_24h_usd": 0.0,
    "open_interest_base": 0.0,
    "open_interest_usd": 0.0,
    "daily_snapshot": "2026-07-05"
  },
  {
    "exchange": "dydx",
    "market_type": "CROSS",
    "symbol_raw": "WOO-USD",
    "leverage_max": 10,
    "price_usd": 0.0117274051,
    "volume_24h_usd": 0.0,
    "open_interest_base": 8340.0,
    "open_interest_usd": 97.80655853399999,
    "daily_snapshot": "2026-07-05"
  },
  {
    "exchange": "dydx",
    "market_type": "CROSS",
    "symbol_raw": "PYTH-USD",
    "leverage_max": 5,
    "price_usd": 0.0394863082,
    "volume_24h_usd": 147.4752,
    "open_interest_base": 2971100.0,
    "open_interest_usd": 117317.77029302,
    "daily_snapshot": "2026-07-05"
  },
  {
    "exchange": "dydx",
    "market_type": "CROSS",
    "symbol_raw": "BONK-USD",
    "leverage_max": 10,
    "price_usd": 4.8e-06,
    "volume_24h_usd": 14171.0666,
    "open_interest_base": 4484800000.0,
    "open_interest_usd": 21527.039999999997,
    "daily_snapshot": "2026-07-05"
  },
  {
    "exchange": "dydx",
    "market_type": "CROSS",
    "symbol_raw": "AGIX-USD",
    "leverage_max": 5,
    "price_usd": 0.5984417141,
    "volume_24h_usd": 0.0,
    "open_interest_base": 0.0,
    "open_interest_usd": 0.0,
    "daily_snapshot": "2026-07-05"
  },
  {
    "exchange": "dydx",
    "market_type": "CROSS",
    "symbol_raw": "RENDER-USD",
    "leverage_max": 5,
    "price_usd": 1.584959241,
    "volume_24h_usd": 3142.568,
    "open_interest_base": 3855.0,
    "open_interest_usd": 6110.017874055,
    "daily_snapshot": "2026-07-05"
  },
  {
    "exchange": "dydx",
    "market_type": "CROSS",
    "symbol_raw": "STX-USD",
    "leverage_max": 10,
    "price_usd": 0.168786269,
    "volume_24h_usd": 0.0,
    "open_interest_base": 10118.0,
    "open_interest_usd": 1707.779469742,
    "daily_snapshot": "2026-07-05"
  },
  {
    "exchange": "dydx",
    "market_type": "CROSS",
    "symbol_raw": "INJ-USD",
    "leverage_max": 5,
    "price_usd": 4.63475567,
    "volume_24h_usd": 1498.6874,
    "open_interest_base": 10245.4,
    "open_interest_usd": 47484.925741417996,
    "daily_snapshot": "2026-07-05"
  },
  {
    "exchange": "dydx",
    "market_type": "CROSS",
    "symbol_raw": "IMX-USD",
    "leverage_max": 5,
    "price_usd": 0.136607107,
    "volume_24h_usd": 544.96191,
    "open_interest_base": 110178.0,
    "open_interest_usd": 15051.097835046001,
    "daily_snapshot": "2026-07-05"
  },
  {
    "exchange": "dydx",
    "market_type": "CROSS",
    "symbol_raw": "HBAR-USD",
    "leverage_max": 5,
    "price_usd": 0.0748208362,
    "volume_24h_usd": 10410.4124,
    "open_interest_base": 158310.0,
    "open_interest_usd": 11844.886578822001,
    "daily_snapshot": "2026-07-05"
  },
  {
    "exchange": "dydx",
    "market_type": "CROSS",
    "symbol_raw": "ALGO-USD",
    "leverage_max": 5,
    "price_usd": 0.0895392845,
    "volume_24h_usd": 9773.3873,
    "open_interest_base": 1306470.0,
    "open_interest_usd": 116980.389020715,
    "daily_snapshot": "2026-07-05"
  },
  {
    "exchange": "dydx",
    "market_type": "CROSS",
    "symbol_raw": "GRT-USD",
    "leverage_max": 10,
    "price_usd": 0.0183353871,
    "volume_24h_usd": 0.0,
    "open_interest_base": 294720.0,
    "open_interest_usd": 5403.8052861119995,
    "daily_snapshot": "2026-07-05"
  },
  {
    "exchange": "dydx",
    "market_type": "CROSS",
    "symbol_raw": "MANA-USD",
    "leverage_max": 5,
    "price_usd": 0.0705015063,
    "volume_24h_usd": 0.0,
    "open_interest_base": 6380.0,
    "open_interest_usd": 449.799610194,
    "daily_snapshot": "2026-07-05"
  },
  {
    "exchange": "dydx",
    "market_type": "CROSS",
    "symbol_raw": "RUNE-USD",
    "leverage_max": 5,
    "price_usd": 0.410729245,
    "volume_24h_usd": 0.0,
    "open_interest_base": 77936.0,
    "open_interest_usd": 32010.59443832,
    "daily_snapshot": "2026-07-05"
  },
  {
    "exchange": "dydx",
    "market_type": "CROSS",
    "symbol_raw": "AXL-USD",
    "leverage_max": 5,
    "price_usd": 0.042935964,
    "volume_24h_usd": 0.0,
    "open_interest_base": 250735.0,
    "open_interest_usd": 10765.54893354,
    "daily_snapshot": "2026-07-05"
  },
  {
    "exchange": "dydx",
    "market_type": "CROSS",
    "symbol_raw": "AEVO-USD",
    "leverage_max": 5,
    "price_usd": 0.019083589,
    "volume_24h_usd": 0.0,
    "open_interest_base": 0.0,
    "open_interest_usd": 0.0,
    "daily_snapshot": "2026-07-05"
  },
  {
    "exchange": "dydx",
    "market_type": "CROSS",
    "symbol_raw": "ASTR-USD",
    "leverage_max": 5,
    "price_usd": 0.0051819503,
    "volume_24h_usd": 0.0,
    "open_interest_base": 37370.0,
    "open_interest_usd": 193.649482711,
    "daily_snapshot": "2026-07-05"
  },
  {
    "exchange": "dydx",
    "market_type": "CROSS",
    "symbol_raw": "SNX-USD",
    "leverage_max": 5,
    "price_usd": 0.225645432,
    "volume_24h_usd": 0.0,
    "open_interest_base": 48388.0,
    "open_interest_usd": 10918.531163616,
    "daily_snapshot": "2026-07-05"
  },
  {
    "exchange": "dydx",
    "market_type": "CROSS",
    "symbol_raw": "ARKM-USD",
    "leverage_max": 5,
    "price_usd": 0.117020426,
    "volume_24h_usd": 272.9588,
    "open_interest_base": 52716.0,
    "open_interest_usd": 6168.848777016,
    "daily_snapshot": "2026-07-05"
  },
  {
    "exchange": "dydx",
    "market_type": "CROSS",
    "symbol_raw": "DYDX-USD",
    "leverage_max": 5,
    "price_usd": 0.125384769,
    "volume_24h_usd": 4095.36204,
    "open_interest_base": 636734.0,
    "open_interest_usd": 79836.74550444601,
    "daily_snapshot": "2026-07-05"
  },
  {
    "exchange": "dydx",
    "market_type": "CROSS",
    "symbol_raw": "CHZ-USD",
    "leverage_max": 5,
    "price_usd": 0.0182,
    "volume_24h_usd": 268.8388,
    "open_interest_base": 80720.0,
    "open_interest_usd": 1469.104,
    "daily_snapshot": "2026-07-05"
  },
  {
    "exchange": "dydx",
    "market_type": "CROSS",
    "symbol_raw": "WIF-USD",
    "leverage_max": 10,
    "price_usd": 0.172646412,
    "volume_24h_usd": 294.17336,
    "open_interest_base": 266429.0,
    "open_interest_usd": 45998.010902748,
    "daily_snapshot": "2026-07-05"
  },
  {
    "exchange": "dydx",
    "market_type": "CROSS",
    "symbol_raw": "ETHFI-USD",
    "leverage_max": 5,
    "price_usd": 0.426620606,
    "volume_24h_usd": 0.9091,
    "open_interest_base": 743.0,
    "open_interest_usd": 316.979110258,
    "daily_snapshot": "2026-07-05"
  },
  {
    "exchange": "dydx",
    "market_type": "CROSS",
    "symbol_raw": "TON-USD",
    "leverage_max": 5,
    "price_usd": 1.723178673,
    "volume_24h_usd": 0.0,
    "open_interest_base": 0.0,
    "open_interest_usd": 0.0,
    "daily_snapshot": "2026-07-05"
  },
  {
    "exchange": "dydx",
    "market_type": "CROSS",
    "symbol_raw": "W-USD",
    "leverage_max": 5,
    "price_usd": 0.0099434946,
    "volume_24h_usd": 0.0,
    "open_interest_base": 516700.0,
    "open_interest_usd": 5137.80365982,
    "daily_snapshot": "2026-07-05"
  },
  {
    "exchange": "dydx",
    "market_type": "ISOLATED",
    "symbol_raw": "MOTHER-USD",
    "leverage_max": 20,
    "price_usd": 0.0115072852,
    "volume_24h_usd": 0.0,
    "open_interest_base": 0.0,
    "open_interest_usd": 0.0,
    "daily_snapshot": "2026-07-05"
  },
  {
    "exchange": "dydx",
    "market_type": "ISOLATED",
    "symbol_raw": "MOG-USD",
    "leverage_max": 20,
    "price_usd": 1.523e-07,
    "volume_24h_usd": 0.0,
    "open_interest_base": 0.0,
    "open_interest_usd": 0.0,
    "daily_snapshot": "2026-07-05"
  },
  {
    "exchange": "dydx",
    "market_type": "ISOLATED",
    "symbol_raw": "GOAT-USD",
    "leverage_max": 20,
    "price_usd": 0.0167676285,
    "volume_24h_usd": 0.0,
    "open_interest_base": 0.0,
    "open_interest_usd": 0.0,
    "daily_snapshot": "2026-07-05"
  },
  {
    "exchange": "dydx",
    "market_type": "ISOLATED",
    "symbol_raw": "TREMP-USD",
    "leverage_max": 20,
    "price_usd": 0.0522455407,
    "volume_24h_usd": 0.0,
    "open_interest_base": 0.0,
    "open_interest_usd": 0.0,
    "daily_snapshot": "2026-07-05"
  },
  {
    "exchange": "dydx",
    "market_type": "ISOLATED",
    "symbol_raw": "BODEN-USD",
    "leverage_max": 20,
    "price_usd": 0.0020638314,
    "volume_24h_usd": 0.0,
    "open_interest_base": 0.0,
    "open_interest_usd": 0.0,
    "daily_snapshot": "2026-07-05"
  },
  {
    "exchange": "dydx",
    "market_type": "CROSS",
    "symbol_raw": "ZRO-USD",
    "leverage_max": 5,
    "price_usd": 0.913302018,
    "volume_24h_usd": 13.566,
    "open_interest_base": 18212.0,
    "open_interest_usd": 16633.056351816,
    "daily_snapshot": "2026-07-05"
  },
  {
    "exchange": "dydx",
    "market_type": "CROSS",
    "symbol_raw": "ZK-USD",
    "leverage_max": 5,
    "price_usd": 0.0106531891,
    "volume_24h_usd": 0.0,
    "open_interest_base": 1872480.0,
    "open_interest_usd": 19947.883525968,
    "daily_snapshot": "2026-07-05"
  },
  {
    "exchange": "dydx",
    "market_type": "ISOLATED",
    "symbol_raw": "TLOS-USD",
    "leverage_max": 20,
    "price_usd": 0.0138306223,
    "volume_24h_usd": 0.0,
    "open_interest_base": 0.0,
    "open_interest_usd": 0.0,
    "daily_snapshot": "2026-07-05"
  },
  {
    "exchange": "dydx",
    "market_type": "CROSS",
    "symbol_raw": "ONDO-USD",
    "leverage_max": 5,
    "price_usd": 0.324725939,
    "volume_24h_usd": 155.7305,
    "open_interest_base": 268550.0,
    "open_interest_usd": 87205.15091845,
    "daily_snapshot": "2026-07-05"
  },
  {
    "exchange": "dydx",
    "market_type": "CROSS",
    "symbol_raw": "ENA-USD",
    "leverage_max": 5,
    "price_usd": 0.0772394194,
    "volume_24h_usd": 1499.5637,
    "open_interest_base": 617330.0,
    "open_interest_usd": 47682.210778201996,
    "daily_snapshot": "2026-07-05"
  },
  {
    "exchange": "dydx",
    "market_type": "ISOLATED",
    "symbol_raw": "IO-USD",
    "leverage_max": 20,
    "price_usd": 0.177993204,
    "volume_24h_usd": 0.0,
    "open_interest_base": 0.0,
    "open_interest_usd": 0.0,
    "daily_snapshot": "2026-07-05"
  },
  {
    "exchange": "dydx",
    "market_type": "ISOLATED",
    "symbol_raw": "AR-USD",
    "leverage_max": 20,
    "price_usd": 1.642,
    "volume_24h_usd": 0.0,
    "open_interest_base": 0.0,
    "open_interest_usd": 0.0,
    "daily_snapshot": "2026-07-05"
  },
  {
    "exchange": "dydx",
    "market_type": "ISOLATED",
    "symbol_raw": "KAS-USD",
    "leverage_max": 20,
    "price_usd": 0.0302522057,
    "volume_24h_usd": 0.0,
    "open_interest_base": 0.0,
    "open_interest_usd": 0.0,
    "daily_snapshot": "2026-07-05"
  },
  {
    "exchange": "dydx",
    "market_type": "ISOLATED",
    "symbol_raw": "NOT-USD",
    "leverage_max": 20,
    "price_usd": 0.00041384138,
    "volume_24h_usd": 0.0,
    "open_interest_base": 0.0,
    "open_interest_usd": 0.0,
    "daily_snapshot": "2026-07-05"
  },
  {
    "exchange": "dydx",
    "market_type": "CROSS",
    "symbol_raw": "ENS-USD",
    "leverage_max": 5,
    "price_usd": 4.27543473,
    "volume_24h_usd": 0.0,
    "open_interest_base": 23.0,
    "open_interest_usd": 98.33499879,
    "daily_snapshot": "2026-07-05"
  },
  {
    "exchange": "dydx",
    "market_type": "CROSS",
    "symbol_raw": "FLOKI-USD",
    "leverage_max": 5,
    "price_usd": 2.3684484e-05,
    "volume_24h_usd": 13.944,
    "open_interest_base": 40090000.0,
    "open_interest_usd": 949.5109635599999,
    "daily_snapshot": "2026-07-05"
  },
  {
    "exchange": "dydx",
    "market_type": "CROSS",
    "symbol_raw": "TAO-USD",
    "leverage_max": 5,
    "price_usd": 211.0327135,
    "volume_24h_usd": 5525.346,
    "open_interest_base": 111.94,
    "open_interest_usd": 23623.00194919,
    "daily_snapshot": "2026-07-05"
  },
  {
    "exchange": "dydx",
    "market_type": "CROSS",
    "symbol_raw": "FTM-USD",
    "leverage_max": 5,
    "price_usd": 0.7723027697,
    "volume_24h_usd": 0.0,
    "open_interest_base": 0.0,
    "open_interest_usd": 0.0,
    "daily_snapshot": "2026-07-05"
  },
  {
    "exchange": "dydx",
    "market_type": "ISOLATED",
    "symbol_raw": "SAFE-USD",
    "leverage_max": 20,
    "price_usd": 0.100745037,
    "volume_24h_usd": 0.0,
    "open_interest_base": 0.0,
    "open_interest_usd": 0.0,
    "daily_snapshot": "2026-07-05"
  },
  {
    "exchange": "dydx",
    "market_type": "ISOLATED",
    "symbol_raw": "TAIKO-USD",
    "leverage_max": 20,
    "price_usd": 0.119311334,
    "volume_24h_usd": 0.0,
    "open_interest_base": 0.0,
    "open_interest_usd": 0.0,
    "daily_snapshot": "2026-07-05"
  },
  {
    "exchange": "dydx",
    "market_type": "ISOLATED",
    "symbol_raw": "AKT-USD",
    "leverage_max": 20,
    "price_usd": 0.512948715,
    "volume_24h_usd": 0.0,
    "open_interest_base": 0.0,
    "open_interest_usd": 0.0,
    "daily_snapshot": "2026-07-05"
  },
  {
    "exchange": "dydx",
    "market_type": "ISOLATED",
    "symbol_raw": "CAKE-USD",
    "leverage_max": 20,
    "price_usd": 1.374327303,
    "volume_24h_usd": 0.0,
    "open_interest_base": 1836.0,
    "open_interest_usd": 2523.264928308,
    "daily_snapshot": "2026-07-05"
  },
  {
    "exchange": "dydx",
    "market_type": "ISOLATED",
    "symbol_raw": "BRETT-USD",
    "leverage_max": 20,
    "price_usd": 0.0076632021,
    "volume_24h_usd": 0.0,
    "open_interest_base": 0.0,
    "open_interest_usd": 0.0,
    "daily_snapshot": "2026-07-05"
  },
  {
    "exchange": "dydx",
    "market_type": "ISOLATED",
    "symbol_raw": "SATS-USD",
    "leverage_max": 20,
    "price_usd": 1.11952424e-08,
    "volume_24h_usd": 0.0,
    "open_interest_base": 0.0,
    "open_interest_usd": 0.0,
    "daily_snapshot": "2026-07-05"
  },
  {
    "exchange": "dydx",
    "market_type": "CROSS",
    "symbol_raw": "BLAST-USD",
    "leverage_max": 5,
    "price_usd": 0.00028420351,
    "volume_24h_usd": 0.0,
    "open_interest_base": 531600.0,
    "open_interest_usd": 151.082585916,
    "daily_snapshot": "2026-07-05"
  },
  {
    "exchange": "dydx",
    "market_type": "CROSS",
    "symbol_raw": "XMR-USD",
    "leverage_max": 5,
    "price_usd": 325.3397961,
    "volume_24h_usd": 5113.3041,
    "open_interest_base": 177.62,
    "open_interest_usd": 57786.854583282,
    "daily_snapshot": "2026-07-05"
  },
  {
    "exchange": "dydx",
    "market_type": "ISOLATED",
    "symbol_raw": "THETA-USD",
    "leverage_max": 20,
    "price_usd": 0.182718271,
    "volume_24h_usd": 0.0,
    "open_interest_base": 0.0,
    "open_interest_usd": 0.0,
    "daily_snapshot": "2026-07-05"
  },
  {
    "exchange": "dydx",
    "market_type": "ISOLATED",
    "symbol_raw": "ENJ-USD",
    "leverage_max": 20,
    "price_usd": 0.0186202078,
    "volume_24h_usd": 0.0,
    "open_interest_base": 0.0,
    "open_interest_usd": 0.0,
    "daily_snapshot": "2026-07-05"
  },
  {
    "exchange": "dydx",
    "market_type": "CROSS",
    "symbol_raw": "1INCH-USD",
    "leverage_max": 5,
    "price_usd": 0.0712528036,
    "volume_24h_usd": 91.2877,
    "open_interest_base": 514530.0,
    "open_interest_usd": 36661.705036308,
    "daily_snapshot": "2026-07-05"
  },
  {
    "exchange": "dydx",
    "market_type": "ISOLATED",
    "symbol_raw": "XTZ-USD",
    "leverage_max": 20,
    "price_usd": 0.3694184718,
    "volume_24h_usd": 0.0,
    "open_interest_base": 0.0,
    "open_interest_usd": 0.0,
    "daily_snapshot": "2026-07-05"
  },
  {
    "exchange": "dydx",
    "market_type": "ISOLATED",
    "symbol_raw": "UMA-USD",
    "leverage_max": 20,
    "price_usd": 0.43845,
    "volume_24h_usd": 0.0,
    "open_interest_base": 0.0,
    "open_interest_usd": 0.0,
    "daily_snapshot": "2026-07-05"
  },
  {
    "exchange": "dydx",
    "market_type": "ISOLATED",
    "symbol_raw": "CVX-USD",
    "leverage_max": 20,
    "price_usd": 1.692,
    "volume_24h_usd": 0.0,
    "open_interest_base": 0.0,
    "open_interest_usd": 0.0,
    "daily_snapshot": "2026-07-05"
  },
  {
    "exchange": "dydx",
    "market_type": "ISOLATED",
    "symbol_raw": "SUSHI-USD",
    "leverage_max": 20,
    "price_usd": 0.209020902,
    "volume_24h_usd": 0.0,
    "open_interest_base": 0.0,
    "open_interest_usd": 0.0,
    "daily_snapshot": "2026-07-05"
  },
  {
    "exchange": "dydx",
    "market_type": "ISOLATED",
    "symbol_raw": "ZRX-USD",
    "leverage_max": 20,
    "price_usd": 0.1038794377,
    "volume_24h_usd": 0.0,
    "open_interest_base": 0.0,
    "open_interest_usd": 0.0,
    "daily_snapshot": "2026-07-05"
  },
  {
    "exchange": "dydx",
    "market_type": "CROSS",
    "symbol_raw": "PENDLE-USD",
    "leverage_max": 5,
    "price_usd": 1.402087057,
    "volume_24h_usd": 111.804,
    "open_interest_base": 8956.0,
    "open_interest_usd": 12557.091682491999,
    "daily_snapshot": "2026-07-05"
  },
  {
    "exchange": "dydx",
    "market_type": "ISOLATED",
    "symbol_raw": "DEGEN-USD",
    "leverage_max": 20,
    "price_usd": 0.000664024581,
    "volume_24h_usd": 0.0,
    "open_interest_base": 0.0,
    "open_interest_usd": 0.0,
    "daily_snapshot": "2026-07-05"
  },
  {
    "exchange": "dydx",
    "market_type": "CROSS",
    "symbol_raw": "MNT-USD",
    "leverage_max": 5,
    "price_usd": 0.4398986695,
    "volume_24h_usd": 33.992,
    "open_interest_base": 14950.0,
    "open_interest_usd": 6576.485109025,
    "daily_snapshot": "2026-07-05"
  },
  {
    "exchange": "dydx",
    "market_type": "ISOLATED",
    "symbol_raw": "JASMY-USD",
    "leverage_max": 20,
    "price_usd": 0.00527673617,
    "volume_24h_usd": 0.0,
    "open_interest_base": 0.0,
    "open_interest_usd": 0.0,
    "daily_snapshot": "2026-07-05"
  },
  {
    "exchange": "dydx",
    "market_type": "ISOLATED",
    "symbol_raw": "CORE-USD",
    "leverage_max": 20,
    "price_usd": 0.02619738,
    "volume_24h_usd": 0.0,
    "open_interest_base": 0.0,
    "open_interest_usd": 0.0,
    "daily_snapshot": "2026-07-05"
  },
  {
    "exchange": "dydx",
    "market_type": "CROSS",
    "symbol_raw": "PEOPLE-USD",
    "leverage_max": 5,
    "price_usd": 0.0053044258,
    "volume_24h_usd": 0.0,
    "open_interest_base": 10000.0,
    "open_interest_usd": 53.044258,
    "daily_snapshot": "2026-07-05"
  },
  {
    "exchange": "dydx",
    "market_type": "ISOLATED",
    "symbol_raw": "GMX-USD",
    "leverage_max": 20,
    "price_usd": 6.72759143,
    "volume_24h_usd": 0.0,
    "open_interest_base": 0.0,
    "open_interest_usd": 0.0,
    "daily_snapshot": "2026-07-05"
  },
  {
    "exchange": "dydx",
    "market_type": "CROSS",
    "symbol_raw": "POPCAT-USD",
    "leverage_max": 5,
    "price_usd": 0.0511,
    "volume_24h_usd": 0.0,
    "open_interest_base": 6520.0,
    "open_interest_usd": 333.172,
    "daily_snapshot": "2026-07-05"
  },
  {
    "exchange": "dydx",
    "market_type": "ISOLATED",
    "symbol_raw": "PRIME-USD",
    "leverage_max": 20,
    "price_usd": 0.44569954,
    "volume_24h_usd": 0.0,
    "open_interest_base": 0.0,
    "open_interest_usd": 0.0,
    "daily_snapshot": "2026-07-05"
  },
  {
    "exchange": "dydx",
    "market_type": "ISOLATED",
    "symbol_raw": "GALA-USD",
    "leverage_max": 20,
    "price_usd": 0.00348567429,
    "volume_24h_usd": 0.0,
    "open_interest_base": 0.0,
    "open_interest_usd": 0.0,
    "daily_snapshot": "2026-07-05"
  },
  {
    "exchange": "dydx",
    "market_type": "ISOLATED",
    "symbol_raw": "AXS-USD",
    "leverage_max": 20,
    "price_usd": 1.015766353,
    "volume_24h_usd": 0.0,
    "open_interest_base": 498.0,
    "open_interest_usd": 505.85164379400004,
    "daily_snapshot": "2026-07-05"
  },
  {
    "exchange": "dydx",
    "market_type": "ISOLATED",
    "symbol_raw": "XAI-USD",
    "leverage_max": 20,
    "price_usd": 0.0096148557,
    "volume_24h_usd": 0.0,
    "open_interest_base": 0.0,
    "open_interest_usd": 0.0,
    "daily_snapshot": "2026-07-05"
  },
  {
    "exchange": "dydx",
    "market_type": "ISOLATED",
    "symbol_raw": "MEW-USD",
    "leverage_max": 20,
    "price_usd": 0.000598005368,
    "volume_24h_usd": 0.0,
    "open_interest_base": 0.0,
    "open_interest_usd": 0.0,
    "daily_snapshot": "2026-07-05"
  },
  {
    "exchange": "dydx",
    "market_type": "CROSS",
    "symbol_raw": "BEAM-USD",
    "leverage_max": 5,
    "price_usd": 0.00151603731,
    "volume_24h_usd": 0.0,
    "open_interest_base": 88900.0,
    "open_interest_usd": 134.775716859,
    "daily_snapshot": "2026-07-05"
  },
  {
    "exchange": "dydx",
    "market_type": "ISOLATED",
    "symbol_raw": "NEO-USD",
    "leverage_max": 20,
    "price_usd": 2.54025402,
    "volume_24h_usd": 0.0,
    "open_interest_base": 0.0,
    "open_interest_usd": 0.0,
    "daily_snapshot": "2026-07-05"
  },
  {
    "exchange": "dydx",
    "market_type": "ISOLATED",
    "symbol_raw": "EGLD-USD",
    "leverage_max": 20,
    "price_usd": 4.5,
    "volume_24h_usd": 0.0,
    "open_interest_base": 0.0,
    "open_interest_usd": 0.0,
    "daily_snapshot": "2026-07-05"
  },
  {
    "exchange": "dydx",
    "market_type": "ISOLATED",
    "symbol_raw": "ALT-USD",
    "leverage_max": 20,
    "price_usd": 0.0076802888,
    "volume_24h_usd": 0.0,
    "open_interest_base": 0.0,
    "open_interest_usd": 0.0,
    "daily_snapshot": "2026-07-05"
  },
  {
    "exchange": "dydx",
    "market_type": "ISOLATED",
    "symbol_raw": "PIXEL-USD",
    "leverage_max": 20,
    "price_usd": 0.0051095,
    "volume_24h_usd": 0.0,
    "open_interest_base": 0.0,
    "open_interest_usd": 0.0,
    "daily_snapshot": "2026-07-05"
  },
  {
    "exchange": "dydx",
    "market_type": "ISOLATED",
    "symbol_raw": "TURBO-USD",
    "leverage_max": 20,
    "price_usd": 0.000996599659,
    "volume_24h_usd": 0.0,
    "open_interest_base": 0.0,
    "open_interest_usd": 0.0,
    "daily_snapshot": "2026-07-05"
  },
  {
    "exchange": "dydx",
    "market_type": "ISOLATED",
    "symbol_raw": "BOME-USD",
    "leverage_max": 20,
    "price_usd": 0.000393064306,
    "volume_24h_usd": 0.0,
    "open_interest_base": 0.0,
    "open_interest_usd": 0.0,
    "daily_snapshot": "2026-07-05"
  },
  {
    "exchange": "dydx",
    "market_type": "ISOLATED",
    "symbol_raw": "TRB-USD",
    "leverage_max": 20,
    "price_usd": 14.6492675,
    "volume_24h_usd": 0.0,
    "open_interest_base": 0.0,
    "open_interest_usd": 0.0,
    "daily_snapshot": "2026-07-05"
  },
  {
    "exchange": "dydx",
    "market_type": "CROSS",
    "symbol_raw": "ZEN-USD",
    "leverage_max": 5,
    "price_usd": 4.179582586,
    "volume_24h_usd": 0.0,
    "open_interest_base": 1028.0,
    "open_interest_usd": 4296.610898408,
    "daily_snapshot": "2026-07-05"
  },
  {
    "exchange": "dydx",
    "market_type": "ISOLATED",
    "symbol_raw": "BICO-USD",
    "leverage_max": 20,
    "price_usd": 0.020491404,
    "volume_24h_usd": 0.0,
    "open_interest_base": 0.0,
    "open_interest_usd": 0.0,
    "daily_snapshot": "2026-07-05"
  },
  {
    "exchange": "dydx",
    "market_type": "ISOLATED",
    "symbol_raw": "OM-USD",
    "leverage_max": 20,
    "price_usd": 0.06827,
    "volume_24h_usd": 0.0,
    "open_interest_base": 0.0,
    "open_interest_usd": 0.0,
    "daily_snapshot": "2026-07-05"
  },
  {
    "exchange": "dydx",
    "market_type": "ISOLATED",
    "symbol_raw": "DMAIL-USD",
    "leverage_max": 20,
    "price_usd": 0.122414688,
    "volume_24h_usd": 0.0,
    "open_interest_base": 0.0,
    "open_interest_usd": 0.0,
    "daily_snapshot": "2026-07-05"
  },
  {
    "exchange": "dydx",
    "market_type": "ISOLATED",
    "symbol_raw": "MAVIA-USD",
    "leverage_max": 20,
    "price_usd": 0.256523043,
    "volume_24h_usd": 0.0,
    "open_interest_base": 0.0,
    "open_interest_usd": 0.0,
    "daily_snapshot": "2026-07-05"
  },
  {
    "exchange": "dydx",
    "market_type": "ISOLATED",
    "symbol_raw": "ZERO-USD",
    "leverage_max": 20,
    "price_usd": 0.0001357133475,
    "volume_24h_usd": 0.0,
    "open_interest_base": 0.0,
    "open_interest_usd": 0.0,
    "daily_snapshot": "2026-07-05"
  },
  {
    "exchange": "dydx",
    "market_type": "ISOLATED",
    "symbol_raw": "VRTX-USD",
    "leverage_max": 20,
    "price_usd": 0.0646862886,
    "volume_24h_usd": 0.0,
    "open_interest_base": 0.0,
    "open_interest_usd": 0.0,
    "daily_snapshot": "2026-07-05"
  },
  {
    "exchange": "dydx",
    "market_type": "ISOLATED",
    "symbol_raw": "MICHI-USD",
    "leverage_max": 20,
    "price_usd": 0.0015868696,
    "volume_24h_usd": 0.0,
    "open_interest_base": 0.0,
    "open_interest_usd": 0.0,
    "daily_snapshot": "2026-07-05"
  },
  {
    "exchange": "dydx",
    "market_type": "ISOLATED",
    "symbol_raw": "AURORA-USD",
    "leverage_max": 20,
    "price_usd": 0.15936812,
    "volume_24h_usd": 0.0,
    "open_interest_base": 0.0,
    "open_interest_usd": 0.0,
    "daily_snapshot": "2026-07-05"
  },
  {
    "exchange": "dydx",
    "market_type": "ISOLATED",
    "symbol_raw": "FOXY-USD",
    "leverage_max": 20,
    "price_usd": 0.00472618214,
    "volume_24h_usd": 0.0,
    "open_interest_base": 0.0,
    "open_interest_usd": 0.0,
    "daily_snapshot": "2026-07-05"
  },
  {
    "exchange": "dydx",
    "market_type": "CROSS",
    "symbol_raw": "PAXG-USD",
    "leverage_max": 5,
    "price_usd": 4164.741155,
    "volume_24h_usd": 3485.3,
    "open_interest_base": 24.523,
    "open_interest_usd": 102131.94734406499,
    "daily_snapshot": "2026-07-05"
  },
  {
    "exchange": "dydx",
    "market_type": "ISOLATED",
    "symbol_raw": "GME-USD",
    "leverage_max": 20,
    "price_usd": 0.002515523236,
    "volume_24h_usd": 0.0,
    "open_interest_base": 0.0,
    "open_interest_usd": 0.0,
    "daily_snapshot": "2026-07-05"
  },
  {
    "exchange": "dydx",
    "market_type": "CROSS",
    "symbol_raw": "DRIFT-USD",
    "leverage_max": 5,
    "price_usd": 0.015999827,
    "volume_24h_usd": 0.0,
    "open_interest_base": 1080.0,
    "open_interest_usd": 17.27981316,
    "daily_snapshot": "2026-07-05"
  },
  {
    "exchange": "dydx",
    "market_type": "ISOLATED",
    "symbol_raw": "EURC-USD",
    "leverage_max": 20,
    "price_usd": 1.0356,
    "volume_24h_usd": 0.0,
    "open_interest_base": 0.0,
    "open_interest_usd": 0.0,
    "daily_snapshot": "2026-07-05"
  },
  {
    "exchange": "dydx",
    "market_type": "ISOLATED",
    "symbol_raw": "RETARDIO-USD",
    "leverage_max": 20,
    "price_usd": 0.0392881969,
    "volume_24h_usd": 0.0,
    "open_interest_base": 0.0,
    "open_interest_usd": 0.0,
    "daily_snapshot": "2026-07-05"
  },
  {
    "exchange": "dydx",
    "market_type": "ISOLATED",
    "symbol_raw": "DAI-USD",
    "leverage_max": 5,
    "price_usd": 1.000015027,
    "volume_24h_usd": 0.0,
    "open_interest_base": 0.0,
    "open_interest_usd": 0.0,
    "daily_snapshot": "2026-07-05"
  },
  {
    "exchange": "dydx",
    "market_type": "ISOLATED",
    "symbol_raw": "OSMO-USD",
    "leverage_max": 5,
    "price_usd": 0.0329,
    "volume_24h_usd": 0.0,
    "open_interest_base": 0.0,
    "open_interest_usd": 0.0,
    "daily_snapshot": "2026-07-05"
  },
  {
    "exchange": "dydx",
    "market_type": "ISOLATED",
    "symbol_raw": "NEIRO-USD",
    "leverage_max": 20,
    "price_usd": 0.00031199999,
    "volume_24h_usd": 0.0,
    "open_interest_base": 0.0,
    "open_interest_usd": 0.0,
    "daily_snapshot": "2026-07-05"
  },
  {
    "exchange": "dydx",
    "market_type": "ISOLATED",
    "symbol_raw": "HNT-USD",
    "leverage_max": 20,
    "price_usd": 1.011366705,
    "volume_24h_usd": 0.0,
    "open_interest_base": 0.0,
    "open_interest_usd": 0.0,
    "daily_snapshot": "2026-07-05"
  },
  {
    "exchange": "dydx",
    "market_type": "ISOLATED",
    "symbol_raw": "TRY-USD",
    "leverage_max": 100,
    "price_usd": 0.02245255713,
    "volume_24h_usd": 0.0,
    "open_interest_base": 0.0,
    "open_interest_usd": 0.0,
    "daily_snapshot": "2026-07-05"
  },
  {
    "exchange": "dydx",
    "market_type": "ISOLATED",
    "symbol_raw": "SUNDOG-USD",
    "leverage_max": 20,
    "price_usd": 0.0064856161,
    "volume_24h_usd": 0.0,
    "open_interest_base": 0.0,
    "open_interest_usd": 0.0,
    "daily_snapshot": "2026-07-05"
  },
  {
    "exchange": "dydx",
    "market_type": "ISOLATED",
    "symbol_raw": "LUCE-USD",
    "leverage_max": 20,
    "price_usd": 0.0081183763,
    "volume_24h_usd": 0.0,
    "open_interest_base": 0.0,
    "open_interest_usd": 0.0,
    "daily_snapshot": "2026-07-05"
  },
  {
    "exchange": "dydx",
    "market_type": "ISOLATED",
    "symbol_raw": "TRUMPWIN-USD",
    "leverage_max": 20,
    "price_usd": 1.0,
    "volume_24h_usd": 0.0,
    "open_interest_base": 0.0,
    "open_interest_usd": 0.0,
    "daily_snapshot": "2026-07-05"
  },
  {
    "exchange": "dydx",
    "market_type": "ISOLATED",
    "symbol_raw": "CETUS-USD",
    "leverage_max": 20,
    "price_usd": 0.01596149037,
    "volume_24h_usd": 0.0,
    "open_interest_base": 0.0,
    "open_interest_usd": 0.0,
    "daily_snapshot": "2026-07-05"
  },
  {
    "exchange": "dydx",
    "market_type": "ISOLATED",
    "symbol_raw": "ZBCN-USD",
    "leverage_max": 20,
    "price_usd": 0.0010295940811,
    "volume_24h_usd": 0.0,
    "open_interest_base": 0.0,
    "open_interest_usd": 0.0,
    "daily_snapshot": "2026-07-05"
  },
  {
    "exchange": "dydx",
    "market_type": "ISOLATED",
    "symbol_raw": "QTUM-USD",
    "leverage_max": 20,
    "price_usd": 0.888264959,
    "volume_24h_usd": 0.0,
    "open_interest_base": 0.0,
    "open_interest_usd": 0.0,
    "daily_snapshot": "2026-07-05"
  },
  {
    "exchange": "dydx",
    "market_type": "ISOLATED",
    "symbol_raw": "ONT-USD",
    "leverage_max": 20,
    "price_usd": 0.0443222162,
    "volume_24h_usd": 0.0,
    "open_interest_base": 0.0,
    "open_interest_usd": 0.0,
    "daily_snapshot": "2026-07-05"
  },
  {
    "exchange": "dydx",
    "market_type": "ISOLATED",
    "symbol_raw": "REN-USD",
    "leverage_max": 20,
    "price_usd": 0.02525494901,
    "volume_24h_usd": 0.0,
    "open_interest_base": 0.0,
    "open_interest_usd": 0.0,
    "daily_snapshot": "2026-07-05"
  },
  {
    "exchange": "dydx",
    "market_type": "ISOLATED",
    "symbol_raw": "PERP-USD",
    "leverage_max": 20,
    "price_usd": 0.0333508325,
    "volume_24h_usd": 0.0,
    "open_interest_base": 0.0,
    "open_interest_usd": 0.0,
    "daily_snapshot": "2026-07-05"
  },
  {
    "exchange": "dydx",
    "market_type": "ISOLATED",
    "symbol_raw": "EUR-USD",
    "leverage_max": 20,
    "price_usd": 1.143159564,
    "volume_24h_usd": 0.0,
    "open_interest_base": 2721.0,
    "open_interest_usd": 3110.537173644,
    "daily_snapshot": "2026-07-05"
  },
  {
    "exchange": "dydx",
    "market_type": "ISOLATED",
    "symbol_raw": "ORDER-USD",
    "leverage_max": 20,
    "price_usd": 0.0522668029,
    "volume_24h_usd": 0.0,
    "open_interest_base": 0.0,
    "open_interest_usd": 0.0,
    "daily_snapshot": "2026-07-05"
  },
  {
    "exchange": "dydx",
    "market_type": "ISOLATED",
    "symbol_raw": "WBTC-USD",
    "leverage_max": 20,
    "price_usd": 101929.20057,
    "volume_24h_usd": 0.0,
    "open_interest_base": 0.0,
    "open_interest_usd": 0.0,
    "daily_snapshot": "2026-07-05"
  },
  {
    "exchange": "dydx",
    "market_type": "ISOLATED",
    "symbol_raw": "CLV-USD",
    "leverage_max": 20,
    "price_usd": 0.0061,
    "volume_24h_usd": 0.0,
    "open_interest_base": 0.0,
    "open_interest_usd": 0.0,
    "daily_snapshot": "2026-07-05"
  },
  {
    "exchange": "dydx",
    "market_type": "ISOLATED",
    "symbol_raw": "USDE-USD",
    "leverage_max": 20,
    "price_usd": 0.9995000499,
    "volume_24h_usd": 0.0,
    "open_interest_base": 0.0,
    "open_interest_usd": 0.0,
    "daily_snapshot": "2026-07-05"
  },
  {
    "exchange": "dydx",
    "market_type": "CROSS",
    "symbol_raw": "POL-USD",
    "leverage_max": 5,
    "price_usd": 0.0729362382,
    "volume_24h_usd": 1124.8114,
    "open_interest_base": 139640.0,
    "open_interest_usd": 10184.816302248,
    "daily_snapshot": "2026-07-05"
  },
  {
    "exchange": "dydx",
    "market_type": "ISOLATED",
    "symbol_raw": "RAY-USD",
    "leverage_max": 20,
    "price_usd": 0.618038196,
    "volume_24h_usd": 0.0,
    "open_interest_base": 0.0,
    "open_interest_usd": 0.0,
    "daily_snapshot": "2026-07-05"
  },
  {
    "exchange": "dydx",
    "market_type": "ISOLATED",
    "symbol_raw": "PNUT-USD",
    "leverage_max": 20,
    "price_usd": 0.045533183,
    "volume_24h_usd": 0.0,
    "open_interest_base": 0.0,
    "open_interest_usd": 0.0,
    "daily_snapshot": "2026-07-05"
  },
  {
    "exchange": "dydx",
    "market_type": "ISOLATED",
    "symbol_raw": "MOODENG-USD",
    "leverage_max": 20,
    "price_usd": 0.04888,
    "volume_24h_usd": 0.0,
    "open_interest_base": 0.0,
    "open_interest_usd": 0.0,
    "daily_snapshot": "2026-07-05"
  },
  {
    "exchange": "dydx",
    "market_type": "ISOLATED",
    "symbol_raw": "ID-USD",
    "leverage_max": 20,
    "price_usd": 0.0427192719,
    "volume_24h_usd": 0.0,
    "open_interest_base": 0.0,
    "open_interest_usd": 0.0,
    "daily_snapshot": "2026-07-05"
  },
  {
    "exchange": "dydx",
    "market_type": "ISOLATED",
    "symbol_raw": "XYO-USD",
    "leverage_max": 20,
    "price_usd": 0.004046596364,
    "volume_24h_usd": 0.0,
    "open_interest_base": 0.0,
    "open_interest_usd": 0.0,
    "daily_snapshot": "2026-07-05"
  },
  {
    "exchange": "dydx",
    "market_type": "CROSS",
    "symbol_raw": "ZEC-USD",
    "leverage_max": 5,
    "price_usd": 456.89605084,
    "volume_24h_usd": 8321.379,
    "open_interest_base": 303.0,
    "open_interest_usd": 138439.50340452,
    "daily_snapshot": "2026-07-05"
  },
  {
    "exchange": "dydx",
    "market_type": "ISOLATED",
    "symbol_raw": "KSM-USD",
    "leverage_max": 20,
    "price_usd": 4.46,
    "volume_24h_usd": 0.0,
    "open_interest_base": 0.0,
    "open_interest_usd": 0.0,
    "daily_snapshot": "2026-07-05"
  },
  {
    "exchange": "dydx",
    "market_type": "ISOLATED",
    "symbol_raw": "GRASS-USD",
    "leverage_max": 20,
    "price_usd": 0.2126,
    "volume_24h_usd": 0.0,
    "open_interest_base": 0.0,
    "open_interest_usd": 0.0,
    "daily_snapshot": "2026-07-05"
  },
  {
    "exchange": "dydx",
    "market_type": "ISOLATED",
    "symbol_raw": "MAD,RAYDIUM,MADHPJRN6BD8T78RSY7NUSUNWWA2HU8BYPOBZPRHBHV-USD",
    "leverage_max": 20,
    "price_usd": 1.17181959e-05,
    "volume_24h_usd": 0.0,
    "open_interest_base": 0.0,
    "open_interest_usd": 0.0,
    "daily_snapshot": "2026-07-05"
  },
  {
    "exchange": "dydx",
    "market_type": "ISOLATED",
    "symbol_raw": "SKL-USD",
    "leverage_max": 20,
    "price_usd": 0.0068361709,
    "volume_24h_usd": 0.0,
    "open_interest_base": 0.0,
    "open_interest_usd": 0.0,
    "daily_snapshot": "2026-07-05"
  },
  {
    "exchange": "dydx",
    "market_type": "CROSS",
    "symbol_raw": "ATH-USD",
    "leverage_max": 5,
    "price_usd": 0.00443203736,
    "volume_24h_usd": 0.0,
    "open_interest_base": 2712900.0,
    "open_interest_usd": 12023.674153944,
    "daily_snapshot": "2026-07-05"
  },
  {
    "exchange": "dydx",
    "market_type": "ISOLATED",
    "symbol_raw": "GHST-USD",
    "leverage_max": 20,
    "price_usd": 0.7408518296,
    "volume_24h_usd": 0.0,
    "open_interest_base": 0.0,
    "open_interest_usd": 0.0,
    "daily_snapshot": "2026-07-05"
  },
  {
    "exchange": "dydx",
    "market_type": "ISOLATED",
    "symbol_raw": "AMPL-USD",
    "leverage_max": 20,
    "price_usd": 1.2639972,
    "volume_24h_usd": 0.0,
    "open_interest_base": 0.0,
    "open_interest_usd": 0.0,
    "daily_snapshot": "2026-07-05"
  },
  {
    "exchange": "dydx",
    "market_type": "ISOLATED",
    "symbol_raw": "HAWKTUAH,RAYDIUM,4GFE6MBDORSY5BLBIUMRGETR6PZCJYFXMDM5EHSGPUMP-USD",
    "leverage_max": 20,
    "price_usd": 0.000182796282,
    "volume_24h_usd": 0.0,
    "open_interest_base": 0.0,
    "open_interest_usd": 0.0,
    "daily_snapshot": "2026-07-05"
  },
  {
    "exchange": "dydx",
    "market_type": "ISOLATED",
    "symbol_raw": "AERO-USD",
    "leverage_max": 20,
    "price_usd": 0.312286543,
    "volume_24h_usd": 0.0,
    "open_interest_base": 0.0,
    "open_interest_usd": 0.0,
    "daily_snapshot": "2026-07-05"
  },
  {
    "exchange": "dydx",
    "market_type": "ISOLATED",
    "symbol_raw": "PIRATE-USD",
    "leverage_max": 20,
    "price_usd": 0.0041347084,
    "volume_24h_usd": 0.0,
    "open_interest_base": 0.0,
    "open_interest_usd": 0.0,
    "daily_snapshot": "2026-07-05"
  },
  {
    "exchange": "dydx",
    "market_type": "ISOLATED",
    "symbol_raw": "POWSCHE,RAYDIUM,8CKISHHJDHJV4LUOIRMLUHQG58CUKBYJRTCP4Z3MCXNF-USD",
    "leverage_max": 20,
    "price_usd": 0.02033770575,
    "volume_24h_usd": 0.0,
    "open_interest_base": 0.0,
    "open_interest_usd": 0.0,
    "daily_snapshot": "2026-07-05"
  },
  {
    "exchange": "dydx",
    "market_type": "ISOLATED",
    "symbol_raw": "BCUT-USD",
    "leverage_max": 20,
    "price_usd": 0.04690073536,
    "volume_24h_usd": 0.0,
    "open_interest_base": 0.0,
    "open_interest_usd": 0.0,
    "daily_snapshot": "2026-07-05"
  },
  {
    "exchange": "dydx",
    "market_type": "ISOLATED",
    "symbol_raw": "VET-USD",
    "leverage_max": 20,
    "price_usd": 0.00732,
    "volume_24h_usd": 0.0,
    "open_interest_base": 0.0,
    "open_interest_usd": 0.0,
    "daily_snapshot": "2026-07-05"
  },
  {
    "exchange": "dydx",
    "market_type": "ISOLATED",
    "symbol_raw": "YFI-USD",
    "leverage_max": 20,
    "price_usd": 2452.23,
    "volume_24h_usd": 0.0,
    "open_interest_base": 0.0,
    "open_interest_usd": 0.0,
    "daily_snapshot": "2026-07-05"
  },
  {
    "exchange": "dydx",
    "market_type": "ISOLATED",
    "symbol_raw": "G-USD",
    "leverage_max": 20,
    "price_usd": 0.00328506886,
    "volume_24h_usd": 0.0,
    "open_interest_base": 0.0,
    "open_interest_usd": 0.0,
    "daily_snapshot": "2026-07-05"
  },
  {
    "exchange": "dydx",
    "market_type": "CROSS",
    "symbol_raw": "MOVE-USD",
    "leverage_max": 5,
    "price_usd": 0.0117873802,
    "volume_24h_usd": 0.0,
    "open_interest_base": 1000.0,
    "open_interest_usd": 11.7873802,
    "daily_snapshot": "2026-07-05"
  },
  {
    "exchange": "dydx",
    "market_type": "CROSS",
    "symbol_raw": "FARTCOIN,RAYDIUM,9BB6NFECJBCTNNLFKO2FQVQBQ8HHM13KCYYCDQBGPUMP-USD",
    "leverage_max": 5,
    "price_usd": 0.1562477682,
    "volume_24h_usd": 0.0,
    "open_interest_base": 90.0,
    "open_interest_usd": 14.062299138,
    "daily_snapshot": "2026-07-05"
  },
  {
    "exchange": "dydx",
    "market_type": "ISOLATED",
    "symbol_raw": "QNT-USD",
    "leverage_max": 20,
    "price_usd": 64.109,
    "volume_24h_usd": 0.0,
    "open_interest_base": 0.0,
    "open_interest_usd": 0.0,
    "daily_snapshot": "2026-07-05"
  },
  {
    "exchange": "dydx",
    "market_type": "ISOLATED",
    "symbol_raw": "MOCA-USD",
    "leverage_max": 20,
    "price_usd": 0.01487400638,
    "volume_24h_usd": 0.0,
    "open_interest_base": 0.0,
    "open_interest_usd": 0.0,
    "daily_snapshot": "2026-07-05"
  },
  {
    "exchange": "dydx",
    "market_type": "CROSS",
    "symbol_raw": "USUAL-USD",
    "leverage_max": 5,
    "price_usd": 0.009213642,
    "volume_24h_usd": 0.0,
    "open_interest_base": 193890.0,
    "open_interest_usd": 1786.4330473799998,
    "daily_snapshot": "2026-07-05"
  },
  {
    "exchange": "dydx",
    "market_type": "ISOLATED",
    "symbol_raw": "THE-USD",
    "leverage_max": 20,
    "price_usd": 0.265408832,
    "volume_24h_usd": 0.0,
    "open_interest_base": 0.0,
    "open_interest_usd": 0.0,
    "daily_snapshot": "2026-07-05"
  },
  {
    "exchange": "dydx",
    "market_type": "ISOLATED",
    "symbol_raw": "PEAQ-USD",
    "leverage_max": 20,
    "price_usd": 0.0142864286,
    "volume_24h_usd": 0.0,
    "open_interest_base": 0.0,
    "open_interest_usd": 0.0,
    "daily_snapshot": "2026-07-05"
  },
  {
    "exchange": "dydx",
    "market_type": "ISOLATED",
    "symbol_raw": "BABYDOGE-USD",
    "leverage_max": 20,
    "price_usd": 4.06472652e-10,
    "volume_24h_usd": 0.0,
    "open_interest_base": 0.0,
    "open_interest_usd": 0.0,
    "daily_snapshot": "2026-07-05"
  },
  {
    "exchange": "dydx",
    "market_type": "ISOLATED",
    "symbol_raw": "GLMR-USD",
    "leverage_max": 20,
    "price_usd": 0.0126512651,
    "volume_24h_usd": 0.0,
    "open_interest_base": 0.0,
    "open_interest_usd": 0.0,
    "daily_snapshot": "2026-07-05"
  },
  {
    "exchange": "dydx",
    "market_type": "ISOLATED",
    "symbol_raw": "SCRT-USD",
    "leverage_max": 20,
    "price_usd": 0.2287813655,
    "volume_24h_usd": 0.0,
    "open_interest_base": 0.0,
    "open_interest_usd": 0.0,
    "daily_snapshot": "2026-07-05"
  },
  {
    "exchange": "dydx",
    "market_type": "ISOLATED",
    "symbol_raw": "ZEREBRO-USD",
    "leverage_max": 20,
    "price_usd": 0.006969303,
    "volume_24h_usd": 0.0,
    "open_interest_base": 0.0,
    "open_interest_usd": 0.0,
    "daily_snapshot": "2026-07-05"
  },
  {
    "exchange": "dydx",
    "market_type": "CROSS",
    "symbol_raw": "MORPHO-USD",
    "leverage_max": 5,
    "price_usd": 1.965551876,
    "volume_24h_usd": 215.354,
    "open_interest_base": 130.0,
    "open_interest_usd": 255.52174388,
    "daily_snapshot": "2026-07-05"
  },
  {
    "exchange": "dydx",
    "market_type": "ISOLATED",
    "symbol_raw": "COOKIE-USD",
    "leverage_max": 20,
    "price_usd": 0.01790089508,
    "volume_24h_usd": 0.0,
    "open_interest_base": 0.0,
    "open_interest_usd": 0.0,
    "daily_snapshot": "2026-07-05"
  },
  {
    "exchange": "dydx",
    "market_type": "ISOLATED",
    "symbol_raw": "VIRTUAL-USD",
    "leverage_max": 20,
    "price_usd": 0.761526152,
    "volume_24h_usd": 0.0,
    "open_interest_base": 0.0,
    "open_interest_usd": 0.0,
    "daily_snapshot": "2026-07-05"
  },
  {
    "exchange": "dydx",
    "market_type": "ISOLATED",
    "symbol_raw": "CIG,RAYDIUM,EXRQAUXS967FDKYMNXO4EQZEQIHEUBSTBCXPXXWPUMP-USD",
    "leverage_max": 20,
    "price_usd": 4.65475918e-05,
    "volume_24h_usd": 0.0,
    "open_interest_base": 0.0,
    "open_interest_usd": 0.0,
    "daily_snapshot": "2026-07-05"
  },
  {
    "exchange": "dydx",
    "market_type": "ISOLATED",
    "symbol_raw": "AITECH-USD",
    "leverage_max": 20,
    "price_usd": 0.00533721895,
    "volume_24h_usd": 0.0,
    "open_interest_base": 0.0,
    "open_interest_usd": 0.0,
    "daily_snapshot": "2026-07-05"
  },
  {
    "exchange": "dydx",
    "market_type": "ISOLATED",
    "symbol_raw": "SAGA-USD",
    "leverage_max": 20,
    "price_usd": 0.02929956,
    "volume_24h_usd": 0.0,
    "open_interest_base": 0.0,
    "open_interest_usd": 0.0,
    "daily_snapshot": "2026-07-05"
  },
  {
    "exchange": "dydx",
    "market_type": "CROSS",
    "symbol_raw": "TRUMP-USD",
    "leverage_max": 5,
    "price_usd": 1.69798121,
    "volume_24h_usd": 3755.47655,
    "open_interest_base": 30240.6,
    "open_interest_usd": 51347.970579126,
    "daily_snapshot": "2026-07-05"
  },
  {
    "exchange": "dydx",
    "market_type": "CROSS",
    "symbol_raw": "PENGU-USD",
    "leverage_max": 5,
    "price_usd": 0.006574,
    "volume_24h_usd": 900.1078,
    "open_interest_base": 1512200.0,
    "open_interest_usd": 9941.2028,
    "daily_snapshot": "2026-07-05"
  },
  {
    "exchange": "dydx",
    "market_type": "ISOLATED",
    "symbol_raw": "AIXBT-USD",
    "leverage_max": 20,
    "price_usd": 0.0269906242,
    "volume_24h_usd": 0.0,
    "open_interest_base": 0.0,
    "open_interest_usd": 0.0,
    "daily_snapshot": "2026-07-05"
  },
  {
    "exchange": "dydx",
    "market_type": "ISOLATED",
    "symbol_raw": "AI16Z-USD",
    "leverage_max": 20,
    "price_usd": 0.055613316,
    "volume_24h_usd": 0.0,
    "open_interest_base": 0.0,
    "open_interest_usd": 0.0,
    "daily_snapshot": "2026-07-05"
  },
  {
    "exchange": "dydx",
    "market_type": "ISOLATED",
    "symbol_raw": "KOMA-USD",
    "leverage_max": 20,
    "price_usd": 0.00630372831,
    "volume_24h_usd": 0.0,
    "open_interest_base": 0.0,
    "open_interest_usd": 0.0,
    "daily_snapshot": "2026-07-05"
  },
  {
    "exchange": "dydx",
    "market_type": "ISOLATED",
    "symbol_raw": "OCEAN,UNISWAP_V3_BASE,0X1D8148823C46B9C55B678CA84BEB82BC3523ADB1-USD",
    "leverage_max": 20,
    "price_usd": 1.3849e-06,
    "volume_24h_usd": 0.0,
    "open_interest_base": 0.0,
    "open_interest_usd": 0.0,
    "daily_snapshot": "2026-07-05"
  },
  {
    "exchange": "dydx",
    "market_type": "ISOLATED",
    "symbol_raw": "ORCA-USD",
    "leverage_max": 20,
    "price_usd": 0.903547008,
    "volume_24h_usd": 0.0,
    "open_interest_base": 0.0,
    "open_interest_usd": 0.0,
    "daily_snapshot": "2026-07-05"
  },
  {
    "exchange": "dydx",
    "market_type": "ISOLATED",
    "symbol_raw": "NFT-USD",
    "leverage_max": 20,
    "price_usd": 3.341334133e-07,
    "volume_24h_usd": 0.0,
    "open_interest_base": 0.0,
    "open_interest_usd": 0.0,
    "daily_snapshot": "2026-07-05"
  },
  {
    "exchange": "dydx",
    "market_type": "ISOLATED",
    "symbol_raw": "MNRY-USD",
    "leverage_max": 20,
    "price_usd": 2.880185e-05,
    "volume_24h_usd": 0.0,
    "open_interest_base": 0.0,
    "open_interest_usd": 0.0,
    "daily_snapshot": "2026-07-05"
  },
  {
    "exchange": "dydx",
    "market_type": "ISOLATED",
    "symbol_raw": "VVV-USD",
    "leverage_max": 20,
    "price_usd": 11.749236074,
    "volume_24h_usd": 0.0,
    "open_interest_base": 0.0,
    "open_interest_usd": 0.0,
    "daily_snapshot": "2026-07-05"
  },
  {
    "exchange": "dydx",
    "market_type": "ISOLATED",
    "symbol_raw": "NMR-USD",
    "leverage_max": 20,
    "price_usd": 7.88539403,
    "volume_24h_usd": 0.0,
    "open_interest_base": 0.0,
    "open_interest_usd": 0.0,
    "daily_snapshot": "2026-07-05"
  },
  {
    "exchange": "dydx",
    "market_type": "CROSS",
    "symbol_raw": "SPX-USD",
    "leverage_max": 5,
    "price_usd": 0.3998199305,
    "volume_24h_usd": 18.945,
    "open_interest_base": 1330.0,
    "open_interest_usd": 531.760507565,
    "daily_snapshot": "2026-07-05"
  },
  {
    "exchange": "dydx",
    "market_type": "ISOLATED",
    "symbol_raw": "VINE-USD",
    "leverage_max": 20,
    "price_usd": 0.0172361203,
    "volume_24h_usd": 0.0,
    "open_interest_base": 0.0,
    "open_interest_usd": 0.0,
    "daily_snapshot": "2026-07-05"
  },
  {
    "exchange": "dydx",
    "market_type": "CROSS",
    "symbol_raw": "BERA-USD",
    "leverage_max": 5,
    "price_usd": 0.20686863,
    "volume_24h_usd": 0.0,
    "open_interest_base": 50.1,
    "open_interest_usd": 10.364118363,
    "daily_snapshot": "2026-07-05"
  },
  {
    "exchange": "dydx",
    "market_type": "ISOLATED",
    "symbol_raw": "KRL-USD",
    "leverage_max": 20,
    "price_usd": 0.1484814393,
    "volume_24h_usd": 0.0,
    "open_interest_base": 0.0,
    "open_interest_usd": 0.0,
    "daily_snapshot": "2026-07-05"
  },
  {
    "exchange": "dydx",
    "market_type": "ISOLATED",
    "symbol_raw": "ME-USD",
    "leverage_max": 20,
    "price_usd": 0.0993,
    "volume_24h_usd": 0.0,
    "open_interest_base": 0.0,
    "open_interest_usd": 0.0,
    "daily_snapshot": "2026-07-05"
  },
  {
    "exchange": "dydx",
    "market_type": "ISOLATED",
    "symbol_raw": "LAYER-USD",
    "leverage_max": 20,
    "price_usd": 0.0898544904,
    "volume_24h_usd": 0.0,
    "open_interest_base": 0.0,
    "open_interest_usd": 0.0,
    "daily_snapshot": "2026-07-05"
  },
  {
    "exchange": "dydx",
    "market_type": "ISOLATED",
    "symbol_raw": "B3-USD",
    "leverage_max": 20,
    "price_usd": 0.00039555,
    "volume_24h_usd": 0.0,
    "open_interest_base": 0.0,
    "open_interest_usd": 0.0,
    "daily_snapshot": "2026-07-05"
  },
  {
    "exchange": "dydx",
    "market_type": "ISOLATED",
    "symbol_raw": "PAIN-USD",
    "leverage_max": 20,
    "price_usd": 1.329747e-06,
    "volume_24h_usd": 0.0,
    "open_interest_base": 0.0,
    "open_interest_usd": 0.0,
    "daily_snapshot": "2026-07-05"
  },
  {
    "exchange": "dydx",
    "market_type": "ISOLATED",
    "symbol_raw": "IP-USD",
    "leverage_max": 20,
    "price_usd": 0.501014577,
    "volume_24h_usd": 0.0,
    "open_interest_base": 0.0,
    "open_interest_usd": 0.0,
    "daily_snapshot": "2026-07-05"
  },
  {
    "exchange": "dydx",
    "market_type": "ISOLATED",
    "symbol_raw": "SDM-USD",
    "leverage_max": 20,
    "price_usd": 0.00024722472,
    "volume_24h_usd": 0.0,
    "open_interest_base": 0.0,
    "open_interest_usd": 0.0,
    "daily_snapshot": "2026-07-05"
  },
  {
    "exchange": "dydx",
    "market_type": "CROSS",
    "symbol_raw": "KAITO-USD",
    "leverage_max": 5,
    "price_usd": 0.5754791484,
    "volume_24h_usd": 0.0,
    "open_interest_base": 0.0,
    "open_interest_usd": 0.0,
    "daily_snapshot": "2026-07-05"
  },
  {
    "exchange": "dydx",
    "market_type": "ISOLATED",
    "symbol_raw": "PI-USD",
    "leverage_max": 20,
    "price_usd": 0.1130071956,
    "volume_24h_usd": 0.0,
    "open_interest_base": 20.0,
    "open_interest_usd": 2.260143912,
    "daily_snapshot": "2026-07-05"
  },
  {
    "exchange": "dydx",
    "market_type": "ISOLATED",
    "symbol_raw": "KDA-USD",
    "leverage_max": 20,
    "price_usd": 0.0373887833,
    "volume_24h_usd": 0.0,
    "open_interest_base": 0.0,
    "open_interest_usd": 0.0,
    "daily_snapshot": "2026-07-05"
  },
  {
    "exchange": "dydx",
    "market_type": "ISOLATED",
    "symbol_raw": "SSV-USD",
    "leverage_max": 20,
    "price_usd": 2.812,
    "volume_24h_usd": 0.0,
    "open_interest_base": 0.0,
    "open_interest_usd": 0.0,
    "daily_snapshot": "2026-07-05"
  },
  {
    "exchange": "dydx",
    "market_type": "CROSS",
    "symbol_raw": "HYPE-USD",
    "leverage_max": 5,
    "price_usd": 68.85064185,
    "volume_24h_usd": 12216.4528,
    "open_interest_base": 2926.5,
    "open_interest_usd": 201491.40337402502,
    "daily_snapshot": "2026-07-05"
  },
  {
    "exchange": "dydx",
    "market_type": "CROSS",
    "symbol_raw": "S-USD",
    "leverage_max": 5,
    "price_usd": 0.0259051311,
    "volume_24h_usd": 0.0,
    "open_interest_base": 0.0,
    "open_interest_usd": 0.0,
    "daily_snapshot": "2026-07-05"
  },
  {
    "exchange": "dydx",
    "market_type": "ISOLATED",
    "symbol_raw": "REZ-USD",
    "leverage_max": 20,
    "price_usd": 0.00292502603,
    "volume_24h_usd": 0.0,
    "open_interest_base": 0.0,
    "open_interest_usd": 0.0,
    "daily_snapshot": "2026-07-05"
  },
  {
    "exchange": "dydx",
    "market_type": "ISOLATED",
    "symbol_raw": "BTRUMP-USD",
    "leverage_max": 20,
    "price_usd": 1.09441211e-06,
    "volume_24h_usd": 0.0,
    "open_interest_base": 0.0,
    "open_interest_usd": 0.0,
    "daily_snapshot": "2026-07-05"
  },
  {
    "exchange": "dydx",
    "market_type": "ISOLATED",
    "symbol_raw": "BANANA-USD",
    "leverage_max": 20,
    "price_usd": 3.33468674,
    "volume_24h_usd": 0.0,
    "open_interest_base": 0.0,
    "open_interest_usd": 0.0,
    "daily_snapshot": "2026-07-05"
  },
  {
    "exchange": "dydx",
    "market_type": "ISOLATED",
    "symbol_raw": "ELX-USD",
    "leverage_max": 20,
    "price_usd": 0.0032877298,
    "volume_24h_usd": 0.0,
    "open_interest_base": 0.0,
    "open_interest_usd": 0.0,
    "daily_snapshot": "2026-07-05"
  },
  {
    "exchange": "dydx",
    "market_type": "ISOLATED",
    "symbol_raw": "GNO-USD",
    "leverage_max": 20,
    "price_usd": 124.98,
    "volume_24h_usd": 0.0,
    "open_interest_base": 0.0,
    "open_interest_usd": 0.0,
    "daily_snapshot": "2026-07-05"
  },
  {
    "exchange": "dydx",
    "market_type": "ISOLATED",
    "symbol_raw": "MAJOR-USD",
    "leverage_max": 20,
    "price_usd": 0.062319404,
    "volume_24h_usd": 0.0,
    "open_interest_base": 0.0,
    "open_interest_usd": 0.0,
    "daily_snapshot": "2026-07-05"
  },
  {
    "exchange": "dydx",
    "market_type": "ISOLATED",
    "symbol_raw": "API3-USD",
    "leverage_max": 20,
    "price_usd": 0.2952295229,
    "volume_24h_usd": 0.0,
    "open_interest_base": 0.0,
    "open_interest_usd": 0.0,
    "daily_snapshot": "2026-07-05"
  },
  {
    "exchange": "dydx",
    "market_type": "ISOLATED",
    "symbol_raw": "ZETA-USD",
    "leverage_max": 20,
    "price_usd": 0.0518851885,
    "volume_24h_usd": 0.0,
    "open_interest_base": 0.0,
    "open_interest_usd": 0.0,
    "daily_snapshot": "2026-07-05"
  },
  {
    "exchange": "dydx",
    "market_type": "ISOLATED",
    "symbol_raw": "NIL-USD",
    "leverage_max": 20,
    "price_usd": 0.0479476027,
    "volume_24h_usd": 0.0,
    "open_interest_base": 0.0,
    "open_interest_usd": 0.0,
    "daily_snapshot": "2026-07-05"
  },
  {
    "exchange": "dydx",
    "market_type": "ISOLATED",
    "symbol_raw": "MELANIA-USD",
    "leverage_max": 20,
    "price_usd": 0.104585,
    "volume_24h_usd": 0.0,
    "open_interest_base": 0.0,
    "open_interest_usd": 0.0,
    "daily_snapshot": "2026-07-05"
  },
  {
    "exchange": "dydx",
    "market_type": "ISOLATED",
    "symbol_raw": "NC-USD",
    "leverage_max": 20,
    "price_usd": 0.00087498681,
    "volume_24h_usd": 0.0,
    "open_interest_base": 0.0,
    "open_interest_usd": 0.0,
    "daily_snapshot": "2026-07-05"
  },
  {
    "exchange": "dydx",
    "market_type": "ISOLATED",
    "symbol_raw": "BADGER-USD",
    "leverage_max": 20,
    "price_usd": 0.3598,
    "volume_24h_usd": 0.0,
    "open_interest_base": 0.0,
    "open_interest_usd": 0.0,
    "daily_snapshot": "2026-07-05"
  },
  {
    "exchange": "dydx",
    "market_type": "ISOLATED",
    "symbol_raw": "GAS-USD",
    "leverage_max": 20,
    "price_usd": 1.564066068,
    "volume_24h_usd": 0.0,
    "open_interest_base": 0.0,
    "open_interest_usd": 0.0,
    "daily_snapshot": "2026-07-05"
  },
  {
    "exchange": "dydx",
    "market_type": "ISOLATED",
    "symbol_raw": "FORTH-USD",
    "leverage_max": 20,
    "price_usd": 0.965324227,
    "volume_24h_usd": 0.0,
    "open_interest_base": 0.0,
    "open_interest_usd": 0.0,
    "daily_snapshot": "2026-07-05"
  },
  {
    "exchange": "dydx",
    "market_type": "ISOLATED",
    "symbol_raw": "TROY-USD",
    "leverage_max": 20,
    "price_usd": 1.57315731e-05,
    "volume_24h_usd": 0.0,
    "open_interest_base": 0.0,
    "open_interest_usd": 0.0,
    "daily_snapshot": "2026-07-05"
  },
  {
    "exchange": "dydx",
    "market_type": "ISOLATED",
    "symbol_raw": "STEEM-USD",
    "leverage_max": 20,
    "price_usd": 0.05963,
    "volume_24h_usd": 0.0,
    "open_interest_base": 0.0,
    "open_interest_usd": 0.0,
    "daily_snapshot": "2026-07-05"
  },
  {
    "exchange": "dydx",
    "market_type": "ISOLATED",
    "symbol_raw": "BABY-USD",
    "leverage_max": 20,
    "price_usd": 0.01114460992,
    "volume_24h_usd": 0.0,
    "open_interest_base": 0.0,
    "open_interest_usd": 0.0,
    "daily_snapshot": "2026-07-05"
  },
  {
    "exchange": "dydx",
    "market_type": "ISOLATED",
    "symbol_raw": "WCT-USD",
    "leverage_max": 20,
    "price_usd": 0.0599259925,
    "volume_24h_usd": 0.0,
    "open_interest_base": 0.0,
    "open_interest_usd": 0.0,
    "daily_snapshot": "2026-07-05"
  },
  {
    "exchange": "dydx",
    "market_type": "ISOLATED",
    "symbol_raw": "AERGO-USD",
    "leverage_max": 20,
    "price_usd": 0.05481761997,
    "volume_24h_usd": 0.0,
    "open_interest_base": 0.0,
    "open_interest_usd": 0.0,
    "daily_snapshot": "2026-07-05"
  },
  {
    "exchange": "dydx",
    "market_type": "ISOLATED",
    "symbol_raw": "VOXEL-USD",
    "leverage_max": 20,
    "price_usd": 0.0084,
    "volume_24h_usd": 0.0,
    "open_interest_base": 0.0,
    "open_interest_usd": 0.0,
    "daily_snapshot": "2026-07-05"
  },
  {
    "exchange": "dydx",
    "market_type": "ISOLATED",
    "symbol_raw": "MAGIC-USD",
    "leverage_max": 20,
    "price_usd": 0.0644,
    "volume_24h_usd": 0.0,
    "open_interest_base": 0.0,
    "open_interest_usd": 0.0,
    "daily_snapshot": "2026-07-05"
  },
  {
    "exchange": "dydx",
    "market_type": "ISOLATED",
    "symbol_raw": "ALPACA-USD",
    "leverage_max": 20,
    "price_usd": 0.001849,
    "volume_24h_usd": 0.0,
    "open_interest_base": 0.0,
    "open_interest_usd": 0.0,
    "daily_snapshot": "2026-07-05"
  },
  {
    "exchange": "dydx",
    "market_type": "ISOLATED",
    "symbol_raw": "SKITTEN-USD",
    "leverage_max": 20,
    "price_usd": 0.018995336972,
    "volume_24h_usd": 0.0,
    "open_interest_base": 0.0,
    "open_interest_usd": 0.0,
    "daily_snapshot": "2026-07-05"
  },
  {
    "exchange": "dydx",
    "market_type": "ISOLATED",
    "symbol_raw": "SIGN-USD",
    "leverage_max": 20,
    "price_usd": 0.04927,
    "volume_24h_usd": 0.0,
    "open_interest_base": 0.0,
    "open_interest_usd": 0.0,
    "daily_snapshot": "2026-07-05"
  },
  {
    "exchange": "dydx",
    "market_type": "ISOLATED",
    "symbol_raw": "IOTX-USD",
    "leverage_max": 20,
    "price_usd": 0.00449491026,
    "volume_24h_usd": 0.0,
    "open_interest_base": 0.0,
    "open_interest_usd": 0.0,
    "daily_snapshot": "2026-07-05"
  },
  {
    "exchange": "dydx",
    "market_type": "ISOLATED",
    "symbol_raw": "DINNER-USD",
    "leverage_max": 20,
    "price_usd": 0.00339191642976,
    "volume_24h_usd": 0.0,
    "open_interest_base": 0.0,
    "open_interest_usd": 0.0,
    "daily_snapshot": "2026-07-05"
  },
  {
    "exchange": "dydx",
    "market_type": "ISOLATED",
    "symbol_raw": "KERNEL-USD",
    "leverage_max": 20,
    "price_usd": 0.0871,
    "volume_24h_usd": 0.0,
    "open_interest_base": 0.0,
    "open_interest_usd": 0.0,
    "daily_snapshot": "2026-07-05"
  },
  {
    "exchange": "dydx",
    "market_type": "ISOLATED",
    "symbol_raw": "SOPH-USD",
    "leverage_max": 20,
    "price_usd": 0.00927,
    "volume_24h_usd": 0.0,
    "open_interest_base": 0.0,
    "open_interest_usd": 0.0,
    "daily_snapshot": "2026-07-05"
  },
  {
    "exchange": "dydx",
    "market_type": "ISOLATED",
    "symbol_raw": "WSTETH-USD",
    "leverage_max": 20,
    "price_usd": 2448.163776,
    "volume_24h_usd": 0.0,
    "open_interest_base": 0.0,
    "open_interest_usd": 0.0,
    "daily_snapshot": "2026-07-05"
  },
  {
    "exchange": "dydx",
    "market_type": "ISOLATED",
    "symbol_raw": "LPT-USD",
    "leverage_max": 20,
    "price_usd": 2.29699999,
    "volume_24h_usd": 0.0,
    "open_interest_base": 0.0,
    "open_interest_usd": 0.0,
    "daily_snapshot": "2026-07-05"
  },
  {
    "exchange": "dydx",
    "market_type": "ISOLATED",
    "symbol_raw": "TIBBIR-USD",
    "leverage_max": 20,
    "price_usd": 1.4820371e-06,
    "volume_24h_usd": 0.0,
    "open_interest_base": 0.0,
    "open_interest_usd": 0.0,
    "daily_snapshot": "2026-07-05"
  },
  {
    "exchange": "dydx",
    "market_type": "ISOLATED",
    "symbol_raw": "LA-USD",
    "leverage_max": 20,
    "price_usd": 0.2192051411,
    "volume_24h_usd": 0.0,
    "open_interest_base": 0.0,
    "open_interest_usd": 0.0,
    "daily_snapshot": "2026-07-05"
  },
  {
    "exchange": "dydx",
    "market_type": "ISOLATED",
    "symbol_raw": "MASK-USD",
    "leverage_max": 20,
    "price_usd": 0.431525115,
    "volume_24h_usd": 0.0,
    "open_interest_base": 0.0,
    "open_interest_usd": 0.0,
    "daily_snapshot": "2026-07-05"
  },
  {
    "exchange": "dydx",
    "market_type": "ISOLATED",
    "symbol_raw": "DAKU-USD",
    "leverage_max": 20,
    "price_usd": 1.5179178e-06,
    "volume_24h_usd": 0.0,
    "open_interest_base": 0.0,
    "open_interest_usd": 0.0,
    "daily_snapshot": "2026-07-05"
  },
  {
    "exchange": "dydx",
    "market_type": "CROSS",
    "symbol_raw": "SYRUP-USD",
    "leverage_max": 5,
    "price_usd": 0.1610395507,
    "volume_24h_usd": 0.0,
    "open_interest_base": 110.0,
    "open_interest_usd": 17.714350577,
    "daily_snapshot": "2026-07-05"
  },
  {
    "exchange": "dydx",
    "market_type": "ISOLATED",
    "symbol_raw": "FLR-USD",
    "leverage_max": 20,
    "price_usd": 0.00754420373,
    "volume_24h_usd": 0.0,
    "open_interest_base": 0.0,
    "open_interest_usd": 0.0,
    "daily_snapshot": "2026-07-05"
  },
  {
    "exchange": "dydx",
    "market_type": "ISOLATED",
    "symbol_raw": "NEWT-USD",
    "leverage_max": 20,
    "price_usd": 0.0733686686,
    "volume_24h_usd": 0.0,
    "open_interest_base": 0.0,
    "open_interest_usd": 0.0,
    "daily_snapshot": "2026-07-05"
  },
  {
    "exchange": "dydx",
    "market_type": "CROSS",
    "symbol_raw": "PUMP-USD",
    "leverage_max": 5,
    "price_usd": 0.001543519866,
    "volume_24h_usd": 2023.0483,
    "open_interest_base": 5971000.0,
    "open_interest_usd": 9216.357119885999,
    "daily_snapshot": "2026-07-05"
  },
  {
    "exchange": "dydx",
    "market_type": "ISOLATED",
    "symbol_raw": "ES-USD",
    "leverage_max": 5,
    "price_usd": 0.1310365521,
    "volume_24h_usd": 0.0,
    "open_interest_base": 0.0,
    "open_interest_usd": 0.0,
    "daily_snapshot": "2026-07-05"
  },
  {
    "exchange": "dydx",
    "market_type": "ISOLATED",
    "symbol_raw": "ACX-USD",
    "leverage_max": 5,
    "price_usd": 0.0338499359,
    "volume_24h_usd": 0.0,
    "open_interest_base": 0.0,
    "open_interest_usd": 0.0,
    "daily_snapshot": "2026-07-05"
  },
  {
    "exchange": "dydx",
    "market_type": "ISOLATED",
    "symbol_raw": "ERA-USD",
    "leverage_max": 5,
    "price_usd": 0.142194312,
    "volume_24h_usd": 0.0,
    "open_interest_base": 0.0,
    "open_interest_usd": 0.0,
    "daily_snapshot": "2026-07-05"
  },
  {
    "exchange": "dydx",
    "market_type": "CROSS",
    "symbol_raw": "ZORA-USD",
    "leverage_max": 5,
    "price_usd": 0.00719107411,
    "volume_24h_usd": 32.775,
    "open_interest_base": 200000.0,
    "open_interest_usd": 1438.214822,
    "daily_snapshot": "2026-07-05"
  },
  {
    "exchange": "dydx",
    "market_type": "CROSS",
    "symbol_raw": "CRO-USD",
    "leverage_max": 5,
    "price_usd": 0.05964500148,
    "volume_24h_usd": 18.0,
    "open_interest_base": 101400.0,
    "open_interest_usd": 6048.003150072,
    "daily_snapshot": "2026-07-05"
  },
  {
    "exchange": "dydx",
    "market_type": "ISOLATED",
    "symbol_raw": "HUMA-USD",
    "leverage_max": 5,
    "price_usd": 0.018085,
    "volume_24h_usd": 0.0,
    "open_interest_base": 0.0,
    "open_interest_usd": 0.0,
    "daily_snapshot": "2026-07-05"
  },
  {
    "exchange": "dydx",
    "market_type": "ISOLATED",
    "symbol_raw": "OMNI-USD",
    "leverage_max": 5,
    "price_usd": 3.699981184,
    "volume_24h_usd": 0.0,
    "open_interest_base": 0.0,
    "open_interest_usd": 0.0,
    "daily_snapshot": "2026-07-05"
  },
  {
    "exchange": "dydx",
    "market_type": "ISOLATED",
    "symbol_raw": "PROVE-USD",
    "leverage_max": 5,
    "price_usd": 0.2665914996,
    "volume_24h_usd": 0.0,
    "open_interest_base": 0.0,
    "open_interest_usd": 0.0,
    "daily_snapshot": "2026-07-05"
  },
  {
    "exchange": "dydx",
    "market_type": "ISOLATED",
    "symbol_raw": "USELESS-USD",
    "leverage_max": 5,
    "price_usd": 0.0711036237,
    "volume_24h_usd": 0.0,
    "open_interest_base": 0.0,
    "open_interest_usd": 0.0,
    "daily_snapshot": "2026-07-05"
  },
  {
    "exchange": "dydx",
    "market_type": "CROSS",
    "symbol_raw": "WLFI-USD",
    "leverage_max": 5,
    "price_usd": 0.0604576796,
    "volume_24h_usd": 641.1331,
    "open_interest_base": 231530.0,
    "open_interest_usd": 13997.766557788,
    "daily_snapshot": "2026-07-05"
  },
  {
    "exchange": "dydx",
    "market_type": "ISOLATED",
    "symbol_raw": "SKY-USD",
    "leverage_max": 5,
    "price_usd": 0.05934513955,
    "volume_24h_usd": 0.0,
    "open_interest_base": 0.0,
    "open_interest_usd": 0.0,
    "daily_snapshot": "2026-07-05"
  },
  {
    "exchange": "dydx",
    "market_type": "ISOLATED",
    "symbol_raw": "TSLAX-USD",
    "leverage_max": 5,
    "price_usd": 401.0830104,
    "volume_24h_usd": 0.0,
    "open_interest_base": 0.02,
    "open_interest_usd": 8.021660208,
    "daily_snapshot": "2026-07-05"
  },
  {
    "exchange": "dydx",
    "market_type": "ISOLATED",
    "symbol_raw": "LINEA-USD",
    "leverage_max": 5,
    "price_usd": 0.00327183641,
    "volume_24h_usd": 0.0,
    "open_interest_base": 0.0,
    "open_interest_usd": 0.0,
    "daily_snapshot": "2026-07-05"
  },
  {
    "exchange": "dydx",
    "market_type": "ISOLATED",
    "symbol_raw": "PROMPT-USD",
    "leverage_max": 5,
    "price_usd": 0.0412720627,
    "volume_24h_usd": 0.0,
    "open_interest_base": 0.0,
    "open_interest_usd": 0.0,
    "daily_snapshot": "2026-07-05"
  },
  {
    "exchange": "dydx",
    "market_type": "ISOLATED",
    "symbol_raw": "HOLO-USD",
    "leverage_max": 5,
    "price_usd": 0.0613130658,
    "volume_24h_usd": 0.0,
    "open_interest_base": 0.0,
    "open_interest_usd": 0.0,
    "daily_snapshot": "2026-07-05"
  },
  {
    "exchange": "dydx",
    "market_type": "ISOLATED",
    "symbol_raw": "IOTA-USD",
    "leverage_max": 5,
    "price_usd": 0.062559,
    "volume_24h_usd": 0.0,
    "open_interest_base": 0.0,
    "open_interest_usd": 0.0,
    "daily_snapshot": "2026-07-05"
  },
  {
    "exchange": "dydx",
    "market_type": "CROSS",
    "symbol_raw": "ASTER-USD",
    "leverage_max": 5,
    "price_usd": 0.635155391,
    "volume_24h_usd": 6938.83261,
    "open_interest_base": 17666.0,
    "open_interest_usd": 11220.655137406,
    "daily_snapshot": "2026-07-05"
  },
  {
    "exchange": "dydx",
    "market_type": "CROSS",
    "symbol_raw": "XPL-USD",
    "leverage_max": 5,
    "price_usd": 0.1054447955,
    "volume_24h_usd": 43.6962,
    "open_interest_base": 83730.0,
    "open_interest_usd": 8828.892727215,
    "daily_snapshot": "2026-07-05"
  },
  {
    "exchange": "dydx",
    "market_type": "CROSS",
    "symbol_raw": "AVNT-USD",
    "leverage_max": 5,
    "price_usd": 0.09508486688,
    "volume_24h_usd": 0.0,
    "open_interest_base": 100.0,
    "open_interest_usd": 9.508486688,
    "daily_snapshot": "2026-07-05"
  },
  {
    "exchange": "dydx",
    "market_type": "ISOLATED",
    "symbol_raw": "GOONER-USD",
    "leverage_max": 5,
    "price_usd": 1.65574e-06,
    "volume_24h_usd": 0.0,
    "open_interest_base": 0.0,
    "open_interest_usd": 0.0,
    "daily_snapshot": "2026-07-05"
  },
  {
    "exchange": "dydx",
    "market_type": "CROSS",
    "symbol_raw": "2Z-USD",
    "leverage_max": 5,
    "price_usd": 0.0692615169,
    "volume_24h_usd": 0.0,
    "open_interest_base": 2940.0,
    "open_interest_usd": 203.628859686,
    "daily_snapshot": "2026-07-05"
  },
  {
    "exchange": "dydx",
    "market_type": "ISOLATED",
    "symbol_raw": "DODGERSWIN-USD",
    "leverage_max": 5,
    "price_usd": 0.9995,
    "volume_24h_usd": 0.0,
    "open_interest_base": 0.0,
    "open_interest_usd": 0.0,
    "daily_snapshot": "2026-07-05"
  },
  {
    "exchange": "dydx",
    "market_type": "CROSS",
    "symbol_raw": "MET-USD",
    "leverage_max": 5,
    "price_usd": 0.1713446497,
    "volume_24h_usd": 0.0,
    "open_interest_base": 1800.0,
    "open_interest_usd": 308.42036945999996,
    "daily_snapshot": "2026-07-05"
  },
  {
    "exchange": "dydx",
    "market_type": "ISOLATED",
    "symbol_raw": "TREE-USD",
    "leverage_max": 5,
    "price_usd": 0.0683007969,
    "volume_24h_usd": 0.0,
    "open_interest_base": 0.0,
    "open_interest_usd": 0.0,
    "daily_snapshot": "2026-07-05"
  },
  {
    "exchange": "dydx",
    "market_type": "CROSS",
    "symbol_raw": "MON-USD",
    "leverage_max": 5,
    "price_usd": 0.0201760785,
    "volume_24h_usd": 0.0,
    "open_interest_base": 499600.0,
    "open_interest_usd": 10079.9688186,
    "daily_snapshot": "2026-07-05"
  },
  {
    "exchange": "dydx",
    "market_type": "ISOLATED",
    "symbol_raw": "PIPPIN-USD",
    "leverage_max": 5,
    "price_usd": 0.0363922934,
    "volume_24h_usd": 0.0,
    "open_interest_base": 0.0,
    "open_interest_usd": 0.0,
    "daily_snapshot": "2026-07-05"
  },
  {
    "exchange": "dydx",
    "market_type": "ISOLATED",
    "symbol_raw": "ANIME-USD",
    "leverage_max": 5,
    "price_usd": 0.004485,
    "volume_24h_usd": 0.0,
    "open_interest_base": 0.0,
    "open_interest_usd": 0.0,
    "daily_snapshot": "2026-07-05"
  },
  {
    "exchange": "dydx",
    "market_type": "ISOLATED",
    "symbol_raw": "DASH-USD",
    "leverage_max": 5,
    "price_usd": 29.61723366,
    "volume_24h_usd": 0.0,
    "open_interest_base": 0.0,
    "open_interest_usd": 0.0,
    "daily_snapshot": "2026-07-05"
  },
  {
    "exchange": "dydx",
    "market_type": "CROSS",
    "symbol_raw": "LIT-USD",
    "leverage_max": 5,
    "price_usd": 2.322924945,
    "volume_24h_usd": 11.482,
    "open_interest_base": 7197.0,
    "open_interest_usd": 16718.090829165,
    "daily_snapshot": "2026-07-05"
  },
  {
    "exchange": "dydx",
    "market_type": "ISOLATED",
    "symbol_raw": "LUNC-USD",
    "leverage_max": 5,
    "price_usd": 4.166178957e-05,
    "volume_24h_usd": 0.0,
    "open_interest_base": 0.0,
    "open_interest_usd": 0.0,
    "daily_snapshot": "2026-07-05"
  },
  {
    "exchange": "dydx",
    "market_type": "ISOLATED",
    "symbol_raw": "XAUT-USD",
    "leverage_max": 5,
    "price_usd": 4159.587169,
    "volume_24h_usd": 0.0,
    "open_interest_base": 0.0,
    "open_interest_usd": 0.0,
    "daily_snapshot": "2026-07-05"
  },
  {
    "exchange": "dydx",
    "market_type": "CROSS",
    "symbol_raw": "WTI-USD",
    "leverage_max": 5,
    "price_usd": 68.9509,
    "volume_24h_usd": 0.0,
    "open_interest_base": 252.2,
    "open_interest_usd": 17389.41698,
    "daily_snapshot": "2026-07-05"
  },
  {
    "exchange": "dydx",
    "market_type": "CROSS",
    "symbol_raw": "XAG-USD",
    "leverage_max": 5,
    "price_usd": 62.87903,
    "volume_24h_usd": 28633.232,
    "open_interest_base": 117.6,
    "open_interest_usd": 7394.573928,
    "daily_snapshot": "2026-07-05"
  },
  {
    "exchange": "dydx",
    "market_type": "ISOLATED",
    "symbol_raw": "XDC-USD",
    "leverage_max": 5,
    "price_usd": 0.02828303018,
    "volume_24h_usd": 0.0,
    "open_interest_base": 600.0,
    "open_interest_usd": 16.969818108000002,
    "daily_snapshot": "2026-07-05"
  }
]